Workbook

Sheet 成本汇总-测算主表
A1: 超大型土石方开挖运输成本测算表
A3: 【岩石选择】
A4: 岩石级别 | B4: Ⅰ极软岩 | C4: 下拉选择岩石级别（Ⅰ~Ⅷ），自动匹配对应参数
A5: 普氏系数f | B5: =IFERROR(VLOOKUP(B4,'基础核心-参数库'!$E$3:$F$10,2,0),5) | C5: 数据来源: GB/T 50218-2014《工程岩体分级标准》普氏系数f = 岩石单轴抗压强度(MPa) ÷ 10
A6: 实体容重(t/m³) | B6: =IFERROR(VLOOKUP(B4,'基础核心-参数库'!$E$3:$G$10,3,0),2.45) | C6: 数据来源: 岩石力学手册/现场实测实体容重 = 岩石密度 × 重力加速度，取值2.3~2.7 t/m³
A7: 松散系数 | B7: =IFERROR(VLOOKUP(B4,'基础核心-参数库'!$E$3:$H$10,4,0),1.42) | C7: 数据来源: 土石方工程定额实测松散系数 = 松散后体积 ÷ 天然密实体积，取值1.1~1.5
A8: 大块率 | B8: =IFERROR(VLOOKUP(B4,'基础核心-参数库'!$E$3:$K$10,7,0),0.1) | C8: 数据来源: 爆破工程经验统计大块率 = 块径>30cm的体积占比，f越大大块率越高
A9: 可预裂 | B9: =IFERROR(VLOOKUP(B4,'基础核心-参数库'!$E$3:$L$10,8,0),"是") | C9: 判断逻辑: Ⅴ级及以上硬岩才需要预裂爆破预裂目的: 保护边坡稳定性，减少超欠挖
A11: 【工艺选择】
A12: 工艺选择 | B12: 直接开挖 | C12: 推荐工艺仅供参考，可手动选择其他工艺对比成本
A13: 推荐工艺 | B13: =IFERROR(VLOOKUP(B4,'基础核心-参数库'!$E$3:$I$10,5,0),"爆破+开挖") | C13: 推荐逻辑: f≤2→直接开挖，f≤5→爆破+开挖，f>5→爆破+二次破碎
A14: 工艺-岩石硬度匹配校验 | B14: =IF(AND(B5>6,B12="直接开挖"),"⚠极硬岩不宜直接开挖",IF(AND(B5<2,B12="爆破+开挖"),"⚠极软岩不宜爆破,请选直接开挖或松土器","✅")) | C14: f>6直接开挖 → 警告，f<2爆破开挖 → 警告。
A16: 【挖装设备选择】
A17: 挖机选择 | B17: W4.5
A18: 挖机来源 | B18: 自有
A19: 推荐挖机 | B19: =IFERROR(INDEX('合理建议表-推荐规则'!$D$3:$D$8,MATCH(B5,'合理建议表-推荐规则'!$A$3:$A$8,1)),"W4.5") | C19: 推荐逻辑: f=1~3→W3.2/W4.5, f=5~8→W5.5挖机斗容与岩石硬度正相关
A21: 【运输设备选择】
A22: 推荐矿卡 | B22: {=IF(OR(B37="下坡",B39="下坡"),"推荐纯电："&IFERROR(INDEX('合理建议表-推荐规则'!$J$3:$J$8,MATCH(B5,'合理建议表-推荐规则'!$A$3:$A$8,1)),""),"推荐柴油："&IFERROR(INDEX('合理建议表-推荐规则'!$K$3:$K$8,MATCH(B5,'合理建议表-推荐规则'!$A$3:$A$8,1)),""))} | C22: 运距≤3km→T65B(短中途), 运距>8km→T91B(长途); 电动条件下推荐E60Y/E75T/E93L
A23: 矿卡选择 | B23: T65B | C23: 代号规则：T=柴油/E=纯电 + 载重吨位 + 品牌首字母。
A24: 矿卡来源 | B24: 自有
A25: 矿卡与运距选择匹配度 | B25: =IF(AND(B36>10,IFERROR(VLOOKUP(B23,'基础核心-参数库'!$A$40:$D$47,4,0),0)<60),"⚠运距长矿卡偏小",IF(AND(B36<3,IFERROR(VLOOKUP(B23,'基础核心-参数库'!$A$40:$D$47,4,0),0)>60),"⚠矿卡偏大不经济","✅")) | C25: 运距>10km矿卡<60t → 警告，运距<3km矿卡>60t → 警告
A27: 【钻孔设备选择】
A28: 推荐钻机 | B28: =IF(AND(B47>15),"KY200",IF(OR(B12="爆破+开挖",B12="爆破+二次破碎+开挖"),IFERROR(INDEX('合理建议表-推荐规则'!$H$3:$H$8,MATCH(B5,'合理建议表-推荐规则'!$A$3:$A$8,1)),"ZG90"),"—")) | C28: 推荐逻辑: f≤3→ZG90, f≤5→ZG120, f>5→ZG150/牙轮硬岩需要更大扭矩钻机。
A29: 钻机选择 | B29: ZG90
A30: 钻机来源 | B30: 自有
A31: 钻机型号-台阶高度匹配校验 | B31: =IF(AND(B47>15,IFERROR(VLOOKUP(B29,'基础核心-参数库'!$A$51:$O$58,15,0),"潜孔")="潜孔"),"⚠台阶>15m宜选用牙轮钻机(KY200/KY250)","✅") | C31: 钻机选择与台阶高度匹配度：台阶>15m用中小型钻机 → 警告
A33: 【运输参数选择】
A34: 场内距离(km) | B34: 2.1
A35: 场外距离(km) | B35: 5
A36: 总运距(km) | B36: =B34+B35 | C36: 经济运距: 自卸车合理运距≤5km，超过考虑皮带/铁路。场内倒运一般0.5~2km
A37: 场内重车方向 | B37: 平路 | C37: 选择平路则坡度应在2%，上下坡坡度应在15%以内。
A38: 场内坡度(%) | B38: 1.5
A39: 场外重车方向 | B39: 平路 | C39: 选择平路则坡度应在2%，上下坡坡度应在15%以内。
A40: 场外坡度(%) | B40: 1
A41: 道路坡度-行驶方向匹配校验 | B41: =IF(AND(B37="平路",B38>2),"⚠平路场内坡度应≤2%",IF(AND(B37<>"平路",B38<2),"⚠上/下坡场内坡度应≥2%",IF(B38>15,"⚠场内坡度>15%",IF(AND(B39="平路",B40>2),"⚠平路场外坡度应≤2%",IF(AND(B39<>"平路",B40<2),"⚠上/下场外坡度应≥2%",IF(B40>15,"⚠场外坡度>15%","✅")))))) | C41: 坡度与方向匹配度：平路坡度>2% → 警告，上下坡坡度<2% → 警告
A43: 【爆破设计参数规划】
A44: 爆破区域长度(m) | B44: 50 | C44: 沿台阶走向的一次爆破长度，用于分摊预裂费用
A45: 爆破区域宽度(m) | B45: 20 | C45: 从预裂孔到最后排主爆孔的总深度
A46: 缓冲孔排数 | B46: 1 | C46: 预裂爆破时在预裂孔后方设置的缓冲孔排数
A47: 台阶高度H(m) | B47: 10 | C47: 合理范围: 5~15m，推荐8~12m台阶太高→安全风险，太低→施工效率低
A48: 台阶坡面角α(°) | B48: 75 | C48: 经验取值: 65°~80°，土质边坡≤60°，岩质边坡≤80°坡面角越小，边坡越稳定
A49: 钻孔倾角(°) | B49: 90 | C49: 钻孔倾角: 垂直孔90°，倾斜孔70°~85°倾斜孔有利于根底处理，但钻孔难度大
A50: 布孔形式 | B50: 矩形 | C50: 布孔形式: 矩形布孔简单，梅花形布孔更均匀宽孔距布孔a/W1=1.5~2.0，降低大块率
A51: 推荐孔径(mm) | B51: =IF(OR(B12="爆破+开挖",B12="爆破+二次破碎+开挖"),IFERROR(INDEX('合理建议表-推荐规则'!$I$3:$I$8,MATCH(B5,'合理建议表-推荐规则'!$A$3:$A$8,1)),90),"—") | C51: 推荐公式: f=1→90mm, f=3→115mm, f=5→138mm, f=8→165mm孔径与台阶高度匹配: H≤10m→90~115mm
A52: 孔径选择(mm) | B52: 90
A53: 是否预裂 | B53: 否 | C53: 判断逻辑: 只有Ⅴ~Ⅷ级硬岩且边坡有保护要求才预裂预裂增加成本约15~20%，需权衡
A54: 台阶高度合理性判断 | B54: =IF(B47>15,"⚠台阶高度偏大,建议5~15m",IF(B47<5,"⚠台阶高度偏小,建议≥5m",IF(AND(B52<90,B47>12),"⚠孔径偏小与台阶不匹配",IF(AND(B47>15,B52<115),"⚠台阶>15m建议孔径≥115mm","✅")))) | C54: 超高/偏低/孔径不匹配 → 警告 情况1：台阶太高：如果台阶高度超过15米→ 提示："台阶高度偏大,建议5~15m"。台阶太高不安全，爆破效果也不好，太高了钻机也够不着。一般露天矿山台阶高度都是5~15米。 情况2：台阶太低：如果台阶高度小于5米→ 提示："台阶高度偏小,建议≥5m"。台阶太低了浪费钻孔，施工效率也低。钻一个10米深的孔和钻一个3米深的孔，钻机辅助时间差不多。 情况3：小孔钻深孔如果孔径不到90mm，但台阶超过12米→ 提示："孔径偏小与台阶不匹配"。就像用细筷子捅深洞，容易断。小孔径钻深孔，钻杆挠度太大，容易偏斜甚至卡钻。 情况4：高台阶必须配大孔径：如果台阶超过15米，但孔径还不到115mm→ 提示："台阶>15m建议孔径≥115mm"。高台阶装药量大，需要大孔径才能装下。同时深孔也需要大直径钻杆保证刚性。
A56: 【直接成本汇总】
A57: 爆破费(元/方) | B57: =IF(AND(B5<2,OR(B12="爆破+开挖",B12="爆破+二次破碎+开挖")),0,IF(OR(B12="爆破+开挖",B12="爆破+二次破碎+开挖"),'计算明细表-钻爆成本'!$B$2,0)) | C57: 条件判断: f<2时不计算爆破费用钻孔爆破费 = 钻机费 + 材料费 + 人工费 + 其他费
A58: 开挖费(元/方) | B58: ='计算明细表-挖装成本'!$B$2 | C58: 挖机台班费÷台班产量实方
A59: 运输费(元/方) | B59: ='计算明细表-运输成本'!$B$2 | C59: 矿卡台班费÷台班运输量（运距为0时运输费=0）
A60: 松土费(元/方) | B60: =IF(B12="松土器松土+开挖",'计算明细表-钩机松土成本'!$B$2,0) | C60: 挖机台班费÷松土器台班产量+齿尖耗材费
A61: 破碎费(元/方) | B61: =IF(B12="机械破碎+开挖",'计算明细表-机械破碎成本'!$B$2,0) | C61: 挖机台班费÷破碎台班产量+钎杆耗材费
A62: 二次破碎费(元/方) | B62: =IF(B12="爆破+二次破碎+开挖",'计算明细表-机械破碎成本'!$B$2*B8,0) | C62: 破碎费×大块率（仅爆破+二次破碎+开挖工艺）
A63: 渣场费(元/方) | B63: ='基础核心-参数库'!$B$11 | C63: 固定值0.5元/方（可在参数库修改）
A64: 综合单价(不含税) | B64: =SUM(B57:B63) | C64: 综合单价(不含税) = 直接成本SUM(B58:B64)
A65: 综合单价(含税) | B65: =B64*(1+'基础核心-参数库'!$B$20) | C65: 参数表基本参数税金设置

Sheet 基础核心-参数库
A1: 【基础价格参数】 | D1: 【岩石分类及开采工艺规则】 | M1: 【工艺错配惩罚系数表】 | Y1: 【通用常量区】
A2: 参数名称 | B2: 数值 | C2: 单位 | D2: 岩石名称 | E2: 岩石级别 | F2: 普氏系数f | G2: 实体容重(t/m³) | H2: 松散系数 | I2: 推荐工艺 | J2: 其他可选工艺 | K2: 爆破大块率 | L2: 可预裂 | M2: 偏离类型 | N2: 效率折减 | O2: 耗材费倍率 | Y2: 参数名称 | Z2: 数值 | AA2: 说明/备注
A3: 柴油单价 | B3: 7.5 | C3: 元/L | D3: 全风化花岗岩 | E3: Ⅰ极软岩 | F3: 0.5 | G3: 1.75 | H3: 1.15 | I3: 直接开挖 | J3: 松土器松土+开挖 | K3: 0 | L3: 否 | M3: 爆破→松土 | N3: 0.2 | O3: 3 | Y3: 矿用运输车折旧维修系数 | Z3: 1.3 | AA3: 运输B68：露天矿1.3~1.8（含日常保养+二级维护）；井下/恶劣矿2.5 | 矿卡折旧维修系数（合同校准）：露天精益承包商下限
A4: 电价(平均) | B4: 0.65 | C4: 元/kWh | D4: 泥岩 | E4: Ⅱ软岩 | F4: 1.5 | G4: 2.1 | H4: 1.25 | I4: 松土器松土+开挖 | J4: 直接开挖,机械破碎+开挖 | K4: 0 | L4: 否 | M4: 爆破→破碎 | N4: 0.5 | O4: 2 | Y4: 挖掘机折旧维修系数 | Z4: 1.5 | AA4: 挖装B28：含液压系统大修+磨耗件，露天1.5~1.8 | 挖掘机折旧维修系数（合同校准）：露天典型中位
A5: 司机机手工日单价 | B5: 300 | C5: 元/工日 | D5: 强风化砂岩 | E5: Ⅲ较软岩 | F5: 3 | G5: 2.3 | H5: 1.35 | I5: 松土器松土+开挖 | J5: 直接开挖,机械破碎+开挖,爆破+开挖 | K5: 0 | L5: 否 | M5: 松土→爆破 | N5: 1 | O5: 1 | Y5: 钻机折旧维修系数 | Z5: 2.2 | AA5: 钻爆B94：钻头钻杆消耗大，系数稍高，1.6~2.0
A6: 乳化炸药单价 | B6: 12 | C6: 元/kg | D6: 中等风化砂岩 | E6: Ⅳ中硬岩 | F6: 5 | G6: 2.45 | H6: 1.42 | I6: 爆破+开挖 | J6: 松土器松土+开挖,机械破碎+开挖,爆破+二次破碎+开挖 | K6: 0.1 | L6: 是 | M6: 松土→破碎 | N6: 0.7 | O6: 1.5 | Y6: 装载机折旧维修系数 | Z6: 1.8 | AA6: 钻爆B11：爆破辅助装载机，1.3~1.8
A7: 雷管单价(数码雷管) | B7: 14 | C7: 元/发 | D7: 微风化花岗岩 | E7: Ⅴ较硬岩 | F7: 7 | G7: 2.6 | H7: 1.48 | I7: 爆破+开挖 | J7: 机械破碎+开挖,爆破+二次破碎+开挖 | K7: 0.12 | L7: 是 | M7: 松土→直接开挖 | N7: 1 | O7: 1 | Y7: 平路油耗负载因子 | Z7: 0.15 | AA7: 运输B59/B61：平路油耗=空车+(上坡-空车)×此值；硬质路0.20，一般0.25，松软0.30 | 平路油耗负载因子（合同校准）：硬质矿山路面
A8: 导爆索单价 | B8: 3 | C8: 元/m | D8: 新鲜花岗岩 | E8: Ⅵ坚硬岩 | F8: 10 | G8: 2.7 | H8: 1.54 | I8: 爆破+开挖 | J8: 爆破+二次破碎+开挖 | K8: 0.18 | L8: 是 | Y8: 矿用车辆耐用年限 | Z8: 8 | AA8: 年；联动矿卡区L40~L47耐用台班=250×此值
A9: 破碎锤钎杆单价 | B9: 1200 | C9: 元/根 | D9: 玄武岩 | E9: Ⅶ极硬岩 | F9: 16 | G9: 2.85 | H9: 1.6 | I9: 爆破+开挖 | J9: 爆破+二次破碎+开挖 | K9: 0.25 | L9: 是 | Y9: 挖掘机耐用年限 | Z9: 10 | AA9: 年；挖机区K26耐用台班=250×此值（K27~K36为型号特异值）
A10: 破碎锤钎杆寿命 | B10: 800 | C10: m³实方 | D10: 致密石英岩 | E10: Ⅷ特殊坚硬岩 | F10: 20 | G10: 3 | H10: 1.65 | I10: 爆破+开挖 | J10: 爆破+二次破碎+开挖 | K10: 0.3 | L10: 是 | Y10: 台班小时数 | Z10: 8 | AA10: h/台班，行业标准（一班制8h，二班制16h）
A11: 渣场维护费 | B11: 0.5 | C11: 元/m³实方 | D11: 【f值相关参数插值基准点】 | Y11: 柴油机械时间利用率 | Z11: 0.75 | AA11: 运输B17、挖装B14、钻爆B93共用；含怠速空驶等无效时间
A12: 松土器齿尖单价 | B12: 600 | C12: 元/个 | D12: 普氏系数f | E12: 钻孔速度系数 | F12: 爆破单耗(kg/m³) | G12: 挖机满斗系数(已弃用) | H12: 松土器效率系数 | I12: 破碎锤效率系数 | J12: 直接开挖折减系数(已弃用) | K12: W1/H系数 | L12: 超深系数 | Y12: 电动机械时间利用率 | Z12: 0.85 | AA12: 电动设备工况系数；同上三处共用
A13: 松土器齿尖寿命 | B13: 2000 | C13: m³实方 | D13: 0.5 | E13: 2.5 | F13: 0 | G13: 0.95 | H13: 2 | I13: 1.2 | J13: 0.95 | K13: 0.9 | L13: 0.12 | Y13: 矿卡时间利用率 | Z13: 0.85 | AA13: 运输B50；含调度/装车排队等待，露天矿0.80~0.90
A14: 机油/液压油单价 | B14: 20 | C14: 元/L | D14: 1 | E14: 2.1 | F14: 0.35 | G14: 0.92 | H14: 1.8 | I14: 1.15 | J14: 0.9 | K14: 0.88 | L14: 0.14 | Y14: 挖机时间利用率 | Z14: 0.75 | AA14: 挖装B22；等车占比最大，露天矿0.75~0.85 | 挖机时间利用率（合同校准）：露天合理上限
A15: 黄油单价 | B15: 15 | C15: 元/kg | D15: 2 | E15: 1.8 | F15: 0.4 | G15: 0.88 | H15: 1.5 | I15: 1.05 | J15: 0.8 | K15: 0.85 | L15: 0.16 | Y15: 钻机时间利用率 | Z15: 0.75 | AA15: 钻爆B87；含换杆/移位/钻头更换，0.65~0.80
A16: 爆破工日工资 | B16: 500 | C16: 元/工日 | D16: 4 | E16: 1.4 | F16: 0.45 | G16: 0.85 | H16: 1 | I16: 0.95 | J16: 0.55 | K16: 0.8 | L16: 0.18 | Y16: 松土器时间利用率 | Z16: 0.7 | AA16: 松土B10；折断/换齿/退车多，0.60~0.75
A17: 单人日装药能力 | B17: 100 | C17: kg/工日 | D17: 6 | E17: 1.05 | F17: 0.52 | G17: 0.78 | H17: 0.55 | I17: 0.88 | J17: 0.25 | K17: 0.75 | L17: 0.2 | Y17: 破碎锤时间利用率 | Z17: 0.65 | AA17: 破碎B10；散热/钎杆更换频繁，0.55~0.70
A18: 年工作台班 | B18: 250 | C18: 台班 | D18: 8 | E18: 0.95 | F18: 0.6 | G18: 0.75 | H18: 0.4 | I18: 0.85 | J18: 0.12 | K18: 0.7 | L18: 0.22 | Y18: 直接开挖装车效率系数 | Z18: 1 | AA18: 挖装B15；岩石原状致密=1.0
A19: 保险费率 | B19: 0.003 | C19: — | D19: 10 | E19: 0.8 | F19: 0.67 | G19: 0.7 | H19: 0.25 | I19: 0.8 | J19: 0.08 | K19: 0.68 | L19: 0.24 | Y19: 爆破后装车效率系数 | Z19: 1.4 | AA19: 挖装B15；岩石松散好装=1.4
A20: 税率 | B20: 0.09 | C20: 增值税 | D20: 14 | E20: 0.6 | F20: 0.74 | G20: 0.62 | H20: 0.08 | I20: 0.7 | J20: 0.04 | K20: 0.65 | L20: 0.26 | Y20: 直接开挖满斗系数 | Z20: 1.05 | AA20: 挖装B19；原状岩斗略冒尖=1.05
A21: 工作面折减系数 | B21: 0.95 | C21: — | D21: 18 | E21: 0.5 | F21: 0.85 | G21: 0.55 | H21: 0 | I21: 0.6 | J21: 0.02 | K21: 0.63 | L21: 0.28 | Y21: 爆破后满斗系数 | Z21: 1.1 | AA21: 挖装B19；爆破块度均匀=1.10
A22: 警戒排险费 | B22: 0.5 | C22: 元/方 | D22: 22 | E22: 0.42 | F22: 1 | G22: 0.5 | H22: 0 | I22: 0.5 | J22: 0.01 | K22: 0.6 | L22: 0.3 | Y22: 松土/破碎斗容利用率 | Z22: 0.85 | AA22: 松土B10/破碎B10；钩头/锤头不同于挖斗，按0.85打折
Y23: 重力加速度g(m/s²) | Z23: 9.81 | AA23: ⚠已废弃（V8删提升高程H后无任何公式引用）：原为重力加速度g，用于爬坡功W=m·g·H
A24: 【挖掘机设备参数】 | Y24: 柴油低位热值(MJ/L) | Z24: 35.86 | AA24: ⚠已废弃（V8删提升高程H后无任何公式引用）：原为0号柴油标准热值，用于爬坡能耗折算
A25: 设备代号 | B25: 品牌 | C25: 型号 | D25: 斗容(m³) | E25: 工作重量(t) | F25: 动力类型 | G25: 功率(kW) | H25: 小时消耗量(L或kWh) | I25: 定员 | J25: 原值(万元) | K25: 耐用台班 | L25: 残值率 | M25: 租赁单价(元/台班) | N25: 斗齿单价(元) | O25: 斗齿寿命(h) | Y25: 坡度上坡油耗修正系数 | Z25: 0.06 | AA25: ⚠已废弃（V8删提升高程H后无任何公式引用）：原为柴油机爬坡综合效率
A26: W1.6 | B26: 三一 | C26: SY365H | D26: 1.6 | E26: 36.5 | F26: 柴油 | G26: 212 | H26: 14 | I26: 1 | J26: 85 | K26: =250*$Z$9 | L26: 0.1 | M26: 1650 | N26: 200 | O26: 800 | Y26: 坡度下坡油耗修正系数 | Z26: 0.03 | AA26: ⚠已废弃（V8删提升高程H后无任何公式引用）：原为电机爬坡综合效率
A27: W2.0 | B27: 卡特彼勒 | C27: 336D | D27: 2 | E27: 34 | F27: 柴油 | G27: 200 | H27: 16 | I27: 1 | J27: 120 | K27: =250*$Z$9 | L27: 0.1 | M27: 2000 | N27: 250 | O27: 750 | Y27: 缓冲孔附加成本系数 | Z27: 0.15
A28: W2.5 | B28: 小松 | C28: PC360 | D28: 2.5 | E28: 36 | F28: 柴油 | G28: 196 | H28: 18 | I28: 1 | J28: 160 | K28: =250*$Z$9 | L28: 0.1 | M28: 2100 | N28: 300 | O28: 700 | Y28: 坡面角修正基准角 | Z28: 75
A29: W3.2 | B29: 沃尔沃 | C29: EC480 | D29: 3.2 | E29: 48 | F29: 柴油 | G29: 265 | H29: 22 | I29: 1 | J29: 220 | K29: =250*$Z$9 | L29: 0.1 | M29: 2900 | N29: 350 | O29: 650 | Y29: 坡面角单耗修正系数 | Z29: 0.008
A30: E2.0 | B30: 三一 | C30: SY365E | D30: 2 | E30: 36.5 | F30: 电动 | G30: 212 | H30: 12.5 | I30: 1 | J30: 160 | K30: =250*$Z$9 | L30: 0.1 | M30: 2200 | N30: 250 | O30: 750 | Y30: 台阶高度修正基准m | Z30: 10
A31: W4.5 | B31: 三一 | C31: SY705H-S | D31: 4.5 | E31: 70 | F31: 柴油 | G31: 350 | H31: 26 | I31: 1 | J31: 250 | K31: =250*$Z$9 | L31: 0.1 | M31: 3500 | N31: 400 | O31: 600 | Y31: 台阶高度单耗修正系数 | Z31: 0.015
A32: W5.5 | B32: 三一 | C32: SY870H-S | D32: 5.5 | E32: 85 | F32: 柴油 | G32: 382 | H32: 30 | I32: 1 | J32: 420 | K32: =250*$Z$9 | L32: 0.1 | M32: 6300 | N32: 450 | O32: 550
A33: W6.5 | B33: 徐工 | C33: XE1050 | D33: 6.5 | E33: 105 | F33: 柴油 | G33: 420 | H33: 34 | I33: 1 | J33: 520 | K33: =250*$Z$9 | L33: 0.1 | M33: 8200 | N33: 500 | O33: 500
A34: W8.0 | B34: 太重 | C34: TZ1000 | D34: 8 | E34: 100 | F34: 柴油 | G34: 510 | H34: 40 | I34: 1 | J34: 650 | K34: =250*$Z$9 | L34: 0.1 | M34: 8500 | N34: 550 | O34: 450
A35: E6.5 | B35: 太重 | C35: TZ1000E | D35: 6.5 | E35: 105 | F35: 电动 | G35: 420 | H35: 26.25 | I35: 1 | J35: 680 | K35: =250*$Z$9 | L35: 0.1 | M35: 8000 | N35: 500 | O35: 500
A36: E8.0 | B36: 沃尔沃 | C36: EC1500E | D36: 8 | E36: 150 | F36: 电动 | G36: 630 | H36: 35 | I36: 1 | J36: 850 | K36: =250*$Z$9 | L36: 0.1 | M36: 9500 | N36: 550 | O36: 450
A38: 【矿用运输车参数】 | R38: 【坡度对速度及油耗/电耗修正系数】 | Y38: 说明：R40:R44是按方向×坡度区间的通用系数表，与矿卡型号无关；故矿卡参数表R45:R47行该区域留空。
A39: 设备代号 | B39: 品牌 | C39: 型号 | D39: 载重(t) | E39: 动力类型 | F39: 功率(kW) | G39: 空载消耗每车(L/km或kWh/km) | H39: 重载上坡油耗(L/km或kWh/km) | I39: 重载下坡油耗(L/km或kWh/km) | J39: 定员 | K39: 原值(万元) | L39: 耐用总台班(年250台班，8年折旧） | M39: 残值率 | N39: 租赁单价(元/台班) | O39: 空车速度(km/h) | P39: 重车速度(km/h) | Q39: 卸车时间(min) | R39: 方向 | S39: 坡度下限(%) | T39: 坡度上限(%) | U39: 空车速度系数 | V39: 重车速度系数 | W39: 柴油油耗系数 | X39: 电动电耗系数 | Y39: ⚠待核：W列油耗系数的"基准坡度"语义需明确——当前W41=W40=1隐含中坡基准
A40: T30H | B40: 中国重汽 | C40: 豪沃TX 8×4 | D40: 30 | E40: 柴油 | F40: 257 | G40: 0.5 | H40: 1.75 | I40: =G40*1.05 | J40: 1 | K40: 35 | L40: =250*$Z$8 | M40: 0.1 | N40: 700 | O40: 35 | P40: 25 | Q40: 1 | R40: 平路 | S40: 0 | T40: 1.99 | U40: 1 | V40: 1 | W40: 1 | X40: 1
A41: E30S | B41: 三一重工 | C41: C8 350kWh 8×4 | D41: 31 | E41: 纯电 | F41: 405 | G41: 0.5 | H41: 1.8 | I41: =G41*1.05 | J41: 1 | K41: 62 | L41: =250*$Z$8 | M41: 0.1 | N41: 1500 | O41: 35 | P41: 25 | Q41: 1 | R41: 上坡 | S41: 2 | T41: 7.99 | U41: 0.85 | V41: 0.75 | W41: 1 | X41: 2.2
A42: T65B | B42: 北方重工 | C42: TR70 | D42: 65 | E42: 柴油 | F42: 520 | G42: 0.85 | H42: 6.13 | I42: =G42*1.05 | J42: 1 | K42: 80 | L42: =250*$Z$8 | M42: 0.1 | N42: 1150 | O42: 30 | P42: 20 | Q42: 1.8 | R42: 上坡 | S42: 8 | T42: 15 | U42: 0.75 | V42: 0.45 | W42: 1.15 | X42: 3
A43: T60S | B43: 三一重工 | C43: SKT90S | D43: 60 | E43: 柴油 | F43: 550 | G43: 1 | H43: 5.6 | I43: =G43*1.05 | J43: 1 | K43: 70 | L43: =250*$Z$8 | M43: 0.1 | N43: 1150 | O43: 30 | P43: 20 | Q43: 1.5 | R43: 下坡 | S43: 2 | T43: 7.99 | U43: 0.9 | V43: 0.9 | W43: 1 | X43: 0.6
A44: T91B | B44: 北方重工 | C44: TR100 | D44: 91 | E44: 柴油 | F44: 703 | G44: 1.11 | H44: 8.1 | I44: =G44*1.05 | J44: 1 | K44: 120 | L44: =250*$Z$8 | M44: 0.1 | N44: 1450 | O44: 28 | P44: 18 | Q44: 2 | R44: 下坡 | S44: 8 | T44: 15 | U44: 0.8 | V44: 0.85 | W44: 0.9 | X44: 0.4
A45: E60Y | B45: 宇通 | C45: YTK90E | D45: 60 | E45: 纯电 | F45: 350 | G45: 0.4 | H45: 3 | I45: =G45*1.05 | J45: 1 | K45: 115 | L45: =250*$Z$8 | M45: 0.1 | N45: 2300 | O45: 30 | P45: 20 | Q45: 1.8
A46: E93L | B46: 临工重机 | C46: RTE136 | D46: 93 | E46: 纯电 | F46: 840 | G46: 0.5 | H46: 4.8 | I46: =G46*1.05 | J46: 1 | K46: 180 | L46: =250*$Z$8 | M46: 0.1 | N46: 3300 | O46: 30 | P46: 20 | Q46: 1.5
A47: E75T | B47: 同力重工 | C47: TLE120 | D47: 75 | E47: 纯电 | F47: 500 | G47: 0.5 | H47: 3.6 | I47: =G47*1.05 | J47: 1 | K47: 145 | L47: =250*$Z$8 | M47: 0.1 | N47: 2700 | O47: 28 | P47: 18 | Q47: 2
A49: 【钻机设备参数】
A50: 设备代号 | B50: 品牌 | C50: 型号 | D50: 动力类型 | E50: 功率(kW) | F50: 换杆方式 | G50: 适用孔径下限(mm) | H50: 适用孔径上限(mm) | I50: 小时消耗量(L/h) | J50: 定员 | K50: 原值(万元) | L50: 耐用总台班 | M50: 残值率 | N50: 租赁单价(元/台班) | O50: 钻机类型
A51: ZG90 | B51: 志高 | C51: ZEGA D480A | D51: 柴油 | E51: 160 | F51: 自动 | G51: 76 | H51: 115 | I51: 10 | J51: 1 | K51: 130 | L51: 4500 | M51: 0.05 | N51: 1500 | O51: 潜孔
A52: ZG120 | B52: 志高 | C52: ZEGA D535 | D52: 柴油 | E52: 220 | F52: 自动 | G52: 89 | H52: 127 | I52: 13.75 | J52: 1 | K52: 190 | L52: 4500 | M52: 0.05 | N52: 2000 | O52: 潜孔
A53: ACD7 | B53: 安百拓 | C53: ROC D7 RRC | D53: 柴油 | E53: 168 | F53: 自动 | G53: 64 | H53: 115 | I53: 10.625 | J53: 1 | K53: 200 | L53: 5000 | M53: 0.05 | N53: 1800 | O53: 潜孔
A54: ACD9 | B54: 安百拓 | C54: ROC D9 RRC | D54: 柴油 | E54: 168 | F54: 自动 | G54: 76 | H54: 115 | I54: 10.625 | J54: 1 | K54: 230 | L54: 5000 | M54: 0.05 | N54: 2100 | O54: 潜孔
A55: AC90 | B55: 安百拓 | C55: FlexiROC T35 | D55: 柴油 | E55: 168 | F55: 人工 | G55: 64 | H55: 115 | I55: 10.625 | J55: 2 | K55: 200 | L55: 5000 | M55: 0.05 | N55: 2300 | O55: 潜孔
A56: AC120 | B56: 安百拓 | C56: FlexiROC T40 | D56: 柴油 | E56: 235 | F56: 人工 | G56: 76 | H56: 115 | I56: 14.375 | J56: 2 | K56: 280 | L56: 5000 | M56: 0.05 | N56: 2900 | O56: 潜孔
A57: KY200 | B57: 国产 | C57: KY-200 | D57: 柴油 | E57: 280 | F57: 自动 | G57: 150 | H57: 200 | I57: 35 | J57: 1.5 | K57: 350 | L57: 5000 | M57: 0.05 | N57: 3500 | O57: 牙轮
A58: KY250 | B58: 国产 | C58: KY-250 | D58: 柴油 | E58: 350 | F58: 自动 | G58: 200 | H58: 250 | I58: 42 | J58: 1.5 | K58: 500 | L58: 5000 | M58: 0.05 | N58: 5000 | O58: 牙轮
A61: 【钻头规格耗材参数（按孔径）】
A62: 设备代号 | B62: 孔径(mm) | C62: 钻头单价(元) | D62: 钻头寿命(m) | E62: 钻杆单价(元) | F62: 钻杆寿命(m) | G62: 冲击器单价(元) | H62: 冲击器寿命(m) | I62: 保养间隔(m) | J62: 保养费用(元/次) | K62: 润滑油消耗率(kg/h) | L62: 孔径速度修正系数
A63: ZG90 | B63: 70 | C63: 600 | D63: 600 | E63: 2500 | F63: 3500 | G63: 4000 | H63: 6000 | I63: 300 | J63: 400 | K63: 0.25 | L63: 1.15
A64: ZG90 | B64: 90 | C64: 800 | D64: 500 | E64: 3000 | F64: 3000 | G64: 5000 | H64: 5000 | I64: 300 | J64: 500 | K64: 0.3 | L64: 1
A65: ZG90 | B65: 115 | C65: 1000 | D65: 400 | E65: 3500 | F65: 2500 | G65: 6000 | H65: 4500 | I65: 300 | J65: 600 | K65: 0.35 | L65: 0.85
A66: ZG120 | B66: 70 | C66: 650 | D66: 550 | E66: 2700 | F66: 3300 | G66: 4300 | H66: 5800 | I66: 300 | J66: 430 | K66: 0.27 | L66: 1.15
A67: ZG120 | B67: 90 | C67: 850 | D67: 480 | E67: 3200 | F67: 2900 | G67: 5300 | H67: 4900 | I67: 300 | J67: 530 | K67: 0.32 | L67: 1
A68: ZG120 | B68: 115 | C68: 1050 | D68: 380 | E68: 3700 | F68: 2400 | G68: 6300 | H68: 4400 | I68: 300 | J68: 630 | K68: 0.37 | L68: 0.85
A69: ACD7 | B69: 70 | C69: 700 | D69: 650 | E69: 2800 | F69: 3700 | G69: 4500 | H69: 6200 | I69: 300 | J69: 450 | K69: 0.26 | L69: 1.15
A70: ACD7 | B70: 90 | C70: 900 | D70: 550 | E70: 3300 | F70: 3200 | G70: 5500 | H70: 5200 | I70: 300 | J70: 550 | K70: 0.31 | L70: 1
A71: ACD7 | B71: 115 | C71: 1100 | D71: 450 | E71: 3800 | F71: 2700 | G71: 6500 | H71: 4700 | I71: 300 | J71: 650 | K71: 0.36 | L71: 0.85
A72: ACD9 | B72: 70 | C72: 720 | D72: 640 | E72: 2850 | F72: 3650 | G72: 4600 | H72: 6100 | I72: 300 | J72: 460 | K72: 0.26 | L72: 1.15
A73: ACD9 | B73: 90 | C73: 920 | D73: 540 | E73: 3350 | F73: 3150 | G73: 5600 | H73: 5100 | I73: 300 | J73: 560 | K73: 0.31 | L73: 1
A74: ACD9 | B74: 115 | C74: 1120 | D74: 440 | E74: 3850 | F74: 2650 | G74: 6600 | H74: 4600 | I74: 300 | J74: 660 | K74: 0.36 | L74: 0.85
... A84: KY250 | B84: 250 | C84: 5000 | D84: 2000 | E84: 15000 | F84: 10000 | G84: 20000 | H84: 14000 | I84: 500 | J84: 2800 | K84: 0.75 | L84: 0.4
A87: 【深孔台阶爆破设计默认值】 | D87: 【装药系数映射表】 | G87: 【孔径-W1映射表】 | J87: 【布孔形式映射表】
A88: 参数名称 | B88: 数值 | C88: 单位 | D88: 孔径(mm) | E88: 装药系数 | F88: 集中装药比例 | G88: 孔径(mm) | H88: W1基准值(m) | J88: 布孔形式 | K88: m值
A89: 台阶高度H | B89: 10 | C89: m | D89: 70 | E89: 0.65 | F89: 0.6 | G89: 70 | H89: 2.1 | J89: 矩形 | K89: 1
A90: 台阶坡面角α | B90: 75 | C90: ° | D90: 90 | E90: 0.7 | F90: 0.5 | G90: 90 | H90: 2.7 | J90: 梅花形 | K90: 1.25
A91: 钻孔倾角 | B91: 90 | C91: ° | D91: 115 | E91: 0.78 | F91: 0.4 | G91: 115 | H91: 3.4 | J91: 宽孔距 | K91: 1.5
A92: 后排阻力系数K | B92: 1.1 | C92: — | D92: 150 | E92: 0.82 | F92: 0.35 | G92: 150 | H92: 4.5
A93: 装药系数 | B93: 0.7 | C93: — | D93: 200 | E93: 0.85 | F93: 0.3 | G93: 200 | H93: 6
A94: 乳化炸药密度 | B94: 1.15 | C94: t/m³ | D94: 250 | E94: 0.88 | F94: 0.25 | G94: 250 | H94: 7.5
A96: 【爆破辅助装载机参数】 | E96: 【钻孔辅助时间参数】
A97: 参数名称 | B97: 数值 | C97: 单位 | E97: 参数名称 | F97: 自动换杆 | G97: 人工换杆 | H97: 单位
A98: 装载机型号 | B98: ZL50 | C98: — | E98: 接杆时间 | F98: 1.5 | G98: 4 | H98: 分钟/根
A99: 功率 | B99: 162 | C99: kW | E99: 卸杆时间 | F99: 1.5 | G99: 3.5 | H99: 分钟/根
A100: 小时油耗 | B100: 12 | C100: L/h | E100: 移位时间 | F100: 2 | G100: 2 | H100: 分钟/孔
A101: 原值 | B101: 35 | C101: 万元 | E101: 清孔时间 | F101: 2 | G101: 2 | H101: 分钟/孔
A102: 耐用总台班 | B102: 4000 | C102: 台班 | E102: 钻杆长度 | F102: 3 | G102: 3 | H102: m/根
A103: 残值率 | B103: 0.05 | C103: — | E103: 时间利用率 | F103: 0.85 | G103: 0.85 | H103: —
A104: 租赁单价 | B104: 1500 | C104: 元/台班
A105: 台班利用系数 | B105: 0.5 | C105: —
A107: 【预裂爆破专用参数】 | E107: 【预裂孔距系数表（K值）】 | H107: 【缓冲孔参数】
A108: 参数名称 | B108: 数值 | C108: 单位 | E108: f值下限 | F108: f值上限 | G108: 孔距系数K | H108: 参数名称 | I108: 数值 | J108: 单位
A109: 预裂孔距系数 | B109: 10 | C109: 倍孔径 | E109: 0 | F109: 4 | G109: 12 | H109: 装药系数（相对主爆孔） | I109: 0.6 | J109: —
A110: 预裂线装药密度 | B110: 0.4 | C110: kg/m | E110: 4 | F110: 6 | G110: 11 | H110: 孔距系数（相对主爆孔） | I110: 0.7 | J110: —
A111: 不耦合系数 | B111: 2.5 | C111: — | E111: 6 | F111: 8 | G111: 10 | H111: 排距系数（相对主爆孔） | I111: 0.8 | J111: —
A112: 预裂孔超深 | B112: 1 | C112: m | E112: 8 | F112: 12 | G112: 9
A113: 底部加强倍数 | B113: 4 | C113: — | E113: 12 | F113: 16 | G113: 8
A114: 预裂每孔雷管数 | B114: 1 | C114: 发
A115: 缓冲排距系数 | B115: 0.6 | C115: 倍主爆排距b
A117: 【松土器台班产量参考（实方/台班，基准配2.0m³挖机）】 | C117: 【破碎锤台班产量参考（实方/台班，基准配2.0m³挖机+140mm锤）】
A118: 岩石f值 | B118: 台班产量(实方) | C118: 岩石f值 | D118: 台班产量(实方)
...

Sheet 合理建议表-推荐规则
A1: 工艺设备推荐表
A2: f下限 | B2: f上限 | C2: 推荐工艺 | D2: 推荐挖机 | E2: 短途矿卡(<3km) | F2: 中途矿卡(3-8km) | G2: 长途矿卡(>8km) | H2: 推荐钻机 | I2: 推荐孔径 | J2: 电动矿卡 | K2: 柴油矿卡
A3: 0 | B3: 0.9 | C3: 直接开挖 | D3: W2.5 | E3: T30H | F3: T30H | G3: T30H | H3: — | I3: — | J3: — | K3: T30H
A4: 1 | B4: 3.9 | C4: 松土器松土+开挖 | D4: W3.2 | E4: T30H | F4: T30H | G4: T65B | H4: — | I4: — | J4: — | K4: T30H
A5: 4 | B5: 5.9 | C5: 爆破+开挖 | D5: W4.5 | E5: T65B | F5: T65B | G5: T91B | H5: ZG90 | I5: 90 | J5: E60Y | K5: T65B
A6: 6 | B6: 7.9 | C6: 爆破+开挖 | D6: W5.5 | E6: T91B | F6: T91B | G6: T91B | H6: AC90 | I6: 90 | J6: E75T | K6: T91B
A7: 8 | B7: 13.9 | C7: 爆破+开挖 | D7: W6.5 | E7: T91B | F7: T91B | G7: T91B | H7: AC120 | I7: 115 | J7: E93L | K7: T91B
A8: 14 | B8: 22 | C8: 爆破+开挖 | D8: W8.0 | E8: T91B | F8: T91B | G8: T91B | H8: AC120 | I8: 115 | J8: E93L | K8: T91B

Sheet 计算明细表-钻爆成本
A1: 钻孔成本计算明细表
A2: 最终爆破成本(元/方) | B2: =B17+B37 | C2: 总爆破成本 = 主爆破费(B17) + 预裂附加费(B37)
A3: 工艺判断 | B3: =IF(ISBLANK('成本汇总-测算主表'!$B$12),"请选择工艺",IF(OR('成本汇总-测算主表'!$B$12="直接开挖",'成本汇总-测算主表'!$B$12="松土器松土+开挖",'成本汇总-测算主表'!$B$12="机械破碎+开挖"),"不适用","正常计算")) | C3: 工艺判断：非"爆破"类工艺时，钻爆所有项归零
A4: --- 单方爆破费用计算明细 ---
A5: 炸药费(元/方) | B5: =IF(OR(B3="不适用",B3="请选择工艺"),0,IFERROR(B56/B72*'基础核心-参数库'!$B$6,0))
A6: 雷管费(元/方) | B6: =IF(OR(B3="不适用",B3="请选择工艺"),0,IFERROR('基础核心-参数库'!$B$7/B72,0)) | C6: 雷管费 = 雷管单价(参数库B7)÷每孔体积；按每孔1发雷管计
A7: 导爆索费(元/方) | B7: =IF(OR(B3="不适用",B3="请选择工艺"),0,IFERROR('基础核心-参数库'!$B$8*B69/B72,0)) | C7: 导爆索费 = 导爆索单价(B8)×孔深(B69)÷每孔体积
A8: 单人日装药孔数 | B8: =IF(OR(B3="不适用",B3="请选择工艺"),0,IFERROR('基础核心-参数库'!$B$17/B56,0)) | C8: 单人日装药孔数 = 单人日装药能力(B17)÷代表单孔药量(B56)
A9: 每日爆破方量 | B9: =B8*B72 | C9: 每日爆破方量 = 日装药孔数(B8) × 每孔体积(B72)
A10: 装药人工费(元/方) | B10: =IF(OR(B3="不适用",B3="请选择工艺"),0,IFERROR('基础核心-参数库'!$B$16/B9,0)) | C10: 装药人工费 = 爆破工日工资(B16)÷每日方量(B9)
A11: 装载机折旧(元/台班) | B11: =IF(OR(B3="不适用",B3="请选择工艺"),0,('基础核心-参数库'!$B$101*10000*(1-'基础核心-参数库'!$B$103)/'基础核心-参数库'!$B$102)*'基础核心-参数库'!$Z$6) | C11: 装载机折旧维修=原值(B101)×(1-残值率B103)÷耐用台班(B102)×系数【常量Z6=1.5】
A12: 装载机能源(元/台班) | B12: =IF(OR(B3="不适用",B3="请选择工艺"),0,'基础核心-参数库'!$B$100*'基础核心-参数库'!$Z$10*'基础核心-参数库'!$B$3/'基础核心-参数库'!$Z$11) | C12: 装载机能源=小时油耗(B100)×台班小时【常量Z10=8】×柴油单价(B3)÷柴油效率【常量Z11=0.75】
A13: 装载机保险(元/台班) | B13: =IF(OR(B3="不适用",B3="请选择工艺"),0,'基础核心-参数库'!$B$101*10000*'基础核心-参数库'!$B$19/'基础核心-参数库'!$B$18) | C13: 装载机保险=原值×保险费率(B19)÷年台班(B18)
A14: 装载机台班费(元) | B14: =B11+B12+B13 | C14: 装载机台班费 = 折旧维修+能源+保险
A15: 装载机辅助费(元/方) | B15: =IF(OR(B3="不适用",B3="请选择工艺"),0,IFERROR(B14*'基础核心-参数库'!$B$105/B9,0)) | C15: 装载机辅助费 = 台班费×台班利用系数(B105)÷服务方量
A16: 警戒排险费(元/方) | B16: =IF(OR(B3="不适用",B3="请选择工艺"),0,'基础核心-参数库'!$B$22) | C16: 警戒排险费：参数库B22默认0.5元/方
A17: 主爆破费(元/方) | B17: =IF(OR(B3="不适用",B3="请选择工艺"),0,(B103+B5+B6+B7+B10+B15+B16)*(1+B22*'基础核心-参数库'!$Z$27)) | C17: 主爆破费 = (钻机摊销+炸药+雷管+索+装药人工+装载机辅助+警戒) × (1 + 缓冲孔排数×Z27=0.15)
A19: --- 预裂爆破计算明细 ---
A20: 爆破长度 L(m) | B20: ='成本汇总-测算主表'!$B$44 | C20: 场地长度 = 主表B44：沿台阶走向的一次爆破长度
A21: 爆破宽度 W(m) | B21: ='成本汇总-测算主表'!$B$45 | C21: 场地宽度 = 主表B45
A22: 缓冲孔排数 | B22: ='成本汇总-测算主表'!$B$46 | C22: 缓冲孔排数 = 主表B46
A23: 预裂孔孔距(m) | B23: =IF(B47="是",IFERROR(SUMIFS('基础核心-参数库'!$G$109:$G$113,'基础核心-参数库'!$E$109:$E$113,"<="&'成本汇总-测算主表'!$B$5,'基础核心-参数库'!$F$109:$F$113,">"&'成本汇总-测算主表'!$B$5)*B49/1000,10*B49/1000),0) | C23: 预裂孔距(m) = SUMIFS按f值查参数库 E109:G113 的孔距系数K × 缓冲排数 ÷ 1000
A24: 预裂孔数量 | B24: =IF(AND(B47="是",B20>0),ROUNDUP(B20/B23,0),0) | C24: 预裂孔数量 = ROUNDUP(场地长度÷预裂孔距)
A25: 预裂单孔钻孔费 | B25: =IF(B47="是",B102*(B40+'基础核心-参数库'!$B$112),0) | C25: 预裂单孔钻孔费 = 钻机每米费(B102)×(台阶高+超钻)
A26: 预裂单孔装药费 | B26: =IF(B47="是",'基础核心-参数库'!$B$110*B20*'基础核心-参数库'!$B$6+'基础核心-参数库'!$B$113*'基础核心-参数库'!$B$110*'基础核心-参数库'!$B$112*'基础核心-参数库'!$B$6,0) | C26: 预裂单孔装药费 = 预裂线装药密度(B110)×台阶高×炸药单价
A27: 预裂单孔雷管费 | B27: =IF(B47="是",'基础核心-参数库'!$B$114*'基础核心-参数库'!$B$7,0) | C27: 预裂单孔雷管费 = 雷管发数(B114)×雷管单价
A28: 预裂单孔总费用 | B28: =B25+B26+B27 | C28: 预裂单孔总费 = 钻孔+装药+雷管
A29: 预裂总费用 | B29: =B24*B28 | C29: 预裂总费用 = 单孔费(B28) × 孔数(B24)
A30: 缓冲孔孔距(m) | B30: =B69*'基础核心-参数库'!$I$110 | C30: 缓冲孔孔距 = 孔距a(B69)×缓冲孔系数(参数库I110)
A31: 缓冲孔排距(m) | B31: =B70*'基础核心-参数库'!$I$111 | C31: 缓冲孔排距 = 排距b(B70)×缓冲孔系数(I111)
A32: 缓冲孔数量 | B32: =IF(AND(B47="是",B22>0,B20>0),ROUNDUP(B20/B30,0)*B22,0) | C32: 缓冲孔数量 = ROUNDUP(长度÷孔距)×排数
A33: 单孔缓冲钻孔费 | B33: =IF(B47="是",B102*B67,0) | C33: 缓冲单孔钻孔费 = 钻机每米费×孔深
A34: 单孔缓冲装药费 | B34: =IF(B47="是",B56*'基础核心-参数库'!$I$109*'基础核心-参数库'!$B$6,0) | C34: 缓冲单孔装药费 = 单耗(B56)×系数(I109)×炸药单价
A35: 单孔缓冲总费用 | B35: =B33+B34 | C35: 缓冲单孔总费 = 钻孔+装药
A36: 缓冲孔总费用 | B36: =B32*B35 | C36: 缓冲孔总费用 = 单孔费 × 孔数
A37: 预裂附加费(元/方) | B37: =IF(AND(B47="是",B20>0,B21>0,'成本汇总-测算主表'!$B$47>0),(B29+B36)/(B20*B21*'成本汇总-测算主表'!$B$47),0) | C37: 预裂附加费(元/方) = (预裂总费+缓冲总费)÷影响范围方量
A39: --- 作业面基本参数汇集 ---
A40: 台阶高度H(m) | B40: ='成本汇总-测算主表'!$B$47 | C40: 台阶高度 = 主表B47
A41: 坡面角α(°) | B41: ='成本汇总-测算主表'!$B$48 | C41: 坡面角 = 主表B48
A42: 钻孔倾角(°) | B42: ='成本汇总-测算主表'!$B$49 | C42: 钻孔倾角 = 主表B49
A43: 布孔形式 | B43: ='成本汇总-测算主表'!$B$50 | C43: 布孔形式 = 主表B50
A44: 孔径(mm) | B44: ='成本汇总-测算主表'!$B$52 | C44: 孔径 = 主表B52
A45: 钻机代号 | B45: ='成本汇总-测算主表'!$B$29 | C45: 钻机代号 = 主表B29
A46: 钻机来源 | B46: ='成本汇总-测算主表'!$B$30 | C46: 钻机来源 = 主表B30
A47: 是否预裂 | B47: =IF(AND('成本汇总-测算主表'!$B$9="是",'成本汇总-测算主表'!$B$5>=5,'成本汇总-测算主表'!$B$53="是"),"是","否") | C47: 是否预裂逻辑：可预裂(主表B9)=是 且 f≥5 且 主表B54=是
A48: 预裂角度 | B48: =IF(B47="是",75,0) | C48: 预裂角度：固定75°（缓冲孔倾向角）
A49: 预裂孔径 | B49: ='成本汇总-测算主表'!$B$52 | C49: 预裂孔径 = 主表B52
A51: --- 装药量参数汇集 ---
A52: 炸药单耗(kg/m³) | B52: =IF(OR(B3="不适用",B3="请选择工艺"),0,(IFERROR(IF('成本汇总-测算主表'!$B$5<='基础核心-参数库'!$D$13,INDEX('基础核心-参数库'!$F$13:$F$22,1),IF('成本汇总-测算主表'!$B$5>='基础核心-参数库'!$D$22,INDEX('基础核心-参数库'!$F$13:$F$22,MATCH('基础核心-参数库'!$D$22,'基础核心-参数库'!$D$13:$D$22,0)),INDEX('基础核心-参数库'!$F$13:$F$22,MATCH('成本汇总-测算主表'!$B$5,'基础核心-参数库'!$D$13:$D$22,1))+('成本汇总-测算主表'!$B$5-INDEX('基础核心-参数库'!$D$13:$D$22,MATCH('成本汇总-测算主表'!$B$5,'基础核心-参数库'!$D$13:$D$22,1)))*(INDEX('基础核心-参数库'!$F$13:$F$22,MATCH('成本汇总-测算主表'!$B$5,'基础核心-参数库'!$D$13:$D$22,1)+1)-INDEX('基础核心-参数库'!$F$13:$F$22,MATCH('成本汇总-测算主表'!$B$5,'基础核心-参数库'!$D$13:$D$22,1)))/(INDEX('基础核心-参数库'!$D$13:$D$22,MATCH('成本汇总-测算主表'!$B$5,'基础核心-参数库'!$D$13:$D$22,1)+1)-INDEX('基础核心-参数库'!$D$13:$D$22,MATCH('成本汇总-测算主表'!$B$5,'基础核心-参数库'!$D$13:$D$22,1))))),0))*(1+MAX(0,'基础核心-参数库'!$Z$28-B41)*'基础核心-参数库'!$Z$29)*(1+ABS(B40-'基础核心-参数库'!$Z$30)/'基础核心-参数库'!$Z$30*'基础核心-参数库'!$Z$31*10)) | C52: 炸药单耗 × 坡面角修正(1+MAX(0,Z28-B41)*Z29) × 台阶高度修正(1+ABS(B40-Z30)/Z30*Z31*10)
A53: 线装药密度(kg/m) | B53: =IF(OR(B3="不适用",B3="请选择工艺"),0,VLOOKUP(B44,'基础核心-参数库'!$D$89:$F$94,2,0)*PI()*(B44/2000)^2*'基础核心-参数库'!$B$94*1000) | C53: 线装药密度 = 按孔径查参数库 D89:F94 的炸药密度系数 × 孔径²系数
A54: 前排药量(kg) | B54: =IF(OR(B3="不适用",B3="请选择工艺"),0,B52*B69*B64*B40) | C54: 前排药量 = 单耗×孔距×超钻系数(B64)×台阶高
A55: 后排药量(kg) | B55: =IF(OR(B3="不适用",B3="请选择工艺"),0,'基础核心-参数库'!$B$92*B52*B69*B70*B40) | C55: 后排药量 = 后排系数(B92)×单耗×孔距×排距(B70)×台阶高
A56: 代表单孔药量(kg) | B56: =B54*0.3+B55*0.7 | C56: 前后排比例按3:7
A57: 装药长度L1(m) | B57: =IFERROR(MIN(B56/B53,B60),0) | C57: 装药长度 = MIN(代表药量÷线装药密度, 最大装药长度)
A58: 堵塞长度L2(m) | B58: =B67-B57 | C58: 堵塞长度 = 孔深(B67) - 装药长度(B57)
A59: 爆破装药安全综合校验 | B59: =IF(B57=0,"⚠装药长度为0",IF(B57>B67,"⚠装药超孔深",IF(OR(B58<30*B44/1000,B58<B64/3,B58<0.9),"⚠堵塞不足",IF(B57<B60,"间隔装药可行,当前连续装药","✅")))) | C59: 安全校验：装药长度=0、超孔深、堵塞不足 → 分级警告
A60: 最大装药长度(m) | B60: =IF(OR(B3="不适用",B3="请选择工艺"),0,B67*VLOOKUP(B44,'基础核心-参数库'!$D$89:$F$94,3,0)) | C60: 最大装药长度 = 孔深×装填系数(参数库)
A62: --- 单孔负担爆破体积计算 ---
A63: 底盘抵抗线台阶高度比值系数 | B63: =IF(OR(B3="不适用",B3="请选择工艺"),0,IFERROR(IF('成本汇总-测算主表'!$B$5<='基础核心-参数库'!$D$13,INDEX('基础核心-参数库'!$K$13:$K$22,1),IF('成本汇总-测算主表'!$B$5>='基础核心-参数库'!$D$22,INDEX('基础核心-参数库'!$K$13:$K$22,MATCH('基础核心-参数库'!$D$22,'基础核心-参数库'!$D$13:$D$22,0)),INDEX('基础核心-参数库'!$K$13:$K$22,MATCH('成本汇总-测算主表'!$B$5,'基础核心-参数库'!$D$13:$D$22,1))+('成本汇总-测算主表'!$B$5-INDEX('基础核心-参数库'!$D$13:$D$22,MATCH('成本汇总-测算主表'!$B$5,'基础核心-参数库'!$D$13:$D$22,1)))*(INDEX('基础核心-参数库'!$K$13:$K$22,MATCH('成本汇总-测算主表'!$B$5,'基础核心-参数库'!$D$13:$D$22,1)+1)-INDEX('基础核心-参数库'!$K$13:$K$22,MATCH('成本汇总-测算主表'!$B$5,'基础核心-参数库'!$D$13:$D$22,1)))/(INDEX('基础核心-参数库'!$D$13:$D$22,MATCH('成本汇总-测算主表'!$B$5,'基础核心-参数库'!$D$13:$D$22,1)+1)-INDEX('基础核心-参数库'!$D$13:$D$22,MATCH('成本汇总-测算主表'!$B$5,'基础核心-参数库'!$D$13:$D$22,1))))),0)) | C63: W1/H系数：f值插值，0.9~0.6，f越大比值越小，控制爆破参数设计合理性。
A64: 底盘抵抗线W1(m) | B64: =IF(OR(B3="不适用",B3="请选择工艺"),0,MIN(VLOOKUP(B44,'基础核心-参数库'!$G$89:$H$94,2,0)*B63,35*B44/1000)) | C64: 底盘抵抗线W1 = MIN(孔径×系数, 孔深÷3)
A65: 台阶爆破超深控制系数 | B65: =IF(OR(B3="不适用",B3="请选择工艺"),0,IFERROR(IF('成本汇总-测算主表'!$B$5<='基础核心-参数库'!$D$13,INDEX('基础核心-参数库'!$L$13:$L$22,1),IF('成本汇总-测算主表'!$B$5>='基础核心-参数库'!$D$22,INDEX('基础核心-参数库'!$L$13:$L$22,MATCH('基础核心-参数库'!$D$22,'基础核心-参数库'!$D$13:$D$22,0)),INDEX('基础核心-参数库'!$L$13:$L$22,MATCH('成本汇总-测算主表'!$B$5,'基础核心-参数库'!$D$13:$D$22,1))+('成本汇总-测算主表'!$B$5-INDEX('基础核心-参数库'!$D$13:$D$22,MATCH('成本汇总-测算主表'!$B$5,'基础核心-参数库'!$D$13:$D$22,1)))*(INDEX('基础核心-参数库'!$L$13:$L$22,MATCH('成本汇总-测算主表'!$B$5,'基础核心-参数库'!$D$13:$D$22,1)+1)-INDEX('基础核心-参数库'!$L$13:$L$22,MATCH('成本汇总-测算主表'!$B$5,'基础核心-参数库'!$D$13:$D$22,1)))/(INDEX('基础核心-参数库'!$D$13:$D$22,MATCH('成本汇总-测算主表'!$B$5,'基础核心-参数库'!$D$13:$D$22,1)+1)-INDEX('基础核心-参数库'!$D$13:$D$22,MATCH('成本汇总-测算主表'!$B$5,'基础核心-参数库'!$D$13:$D$22,1))))),0)) | C65: 超深系数：f值插值，0.12~0.3，f越大超深越大，防止根底产生。
A66: 超深h(m) | B66: =IF(OR(B3="不适用",B3="请选择工艺"),0,MAX(0.15*B64,8*B44/1000)) | C66: 超深h = MAX(0.15×底盘抵抗线, 8×孔径÷1000)
A67: 孔深L(m) | B67: =IF(OR(B3="不适用",B3="请选择工艺"),0,IF(B42=90,B40+B66,(B40+B66)/SIN(RADIANS(B42)))) | C67: 孔深L = (台阶高+超深)÷sin(倾角)；垂直孔时=台阶高+超深
A68: m值 | B68: =IF(B43="矩形",1,IF(B43="梅花形",1.25,1.5)) | C68: 布孔形式对孔距排距影响系数
A69: 孔距a(m) | B69: =IF(OR(B3="不适用",B3="请选择工艺"),0,B68*B64) | C69: 孔距a = m值 × 底盘抵抗线W1
A70: 排距b(m) | B70: =IF(OR(B3="不适用",B3="请选择工艺"),0,IF(B43="矩形",0.9*B64,0.87*B69)) | C70: 排距b：矩形=0.9×W1，梅花/三角=0.87×孔距a
A71: 每米爆破方量(m³/m) | B71: =IF(OR(B3="不适用",B3="请选择工艺"),0,B69*B70) | C71: 每米爆破方量 = 孔距 × 排距
A72: 每孔负担体积(m³) | B72: =IF(OR(B3="不适用",B3="请选择工艺"),0,B69*B70*B40) | C72: 每孔负担体积 = 孔距 × 排距 × 台阶高
A74: --- 台班钻孔工程量计算 ---
A75: 岩石硬度钻孔速度系数 | B75: =IF(OR(B3="不适用",B3="请选择工艺"),0,IFERROR(IF('成本汇总-测算主表'!$B$5<='基础核心-参数库'!$D$13,INDEX('基础核心-参数库'!$E$13:$E$22,1),IF('成本汇总-测算主表'!$B$5>='基础核心-参数库'!$D$22,INDEX('基础核心-参数库'!$E$13:$E$22,MATCH('基础核心-参数库'!$D$22,'基础核心-参数库'!$D$13:$D$22,0)),INDEX('基础核心-参数库'!$E$13:$E$22,MATCH('成本汇总-测算主表'!$B$5,'基础核心-参数库'!$D$13:$D$22,1))+('成本汇总-测算主表'!$B$5-INDEX('基础核心-参数库'!$D$13:$D$22,MATCH('成本汇总-测算主表'!$B$5,'基础核心-参数库'!$D$13:$D$22,1)))*(INDEX('基础核心-参数库'!$E$13:$E$22,MATCH('成本汇总-测算主表'!$B$5,'基础核心-参数库'!$D$13:$D$22,1)+1)-INDEX('基础核心-参数库'!$E$13:$E$22,MATCH('成本汇总-测算主表'!$B$5,'基础核心-参数库'!$D$13:$D$22,1)))/(INDEX('基础核心-参数库'!$D$13:$D$22,MATCH('成本汇总-测算主表'!$B$5,'基础核心-参数库'!$D$13:$D$22,1)+1)-INDEX('基础核心-参数库'!$D$13:$D$22,MATCH('成本汇总-测算主表'!$B$5,'基础核心-参数库'!$D$13:$D$22,1))))),0)) | C75: 钻速系数：f值插值，2.5~0.42，f越大钻速越慢。计算钻孔台班进尺的核心参数。
A76: 钻机型号孔径匹配修正系数 | B76: =IF(OR(B3="不适用",B3="请选择工艺"),1,IFERROR(INDEX('基础核心-参数库'!$L$63:$L$84,MATCH(1,INDEX(('基础核心-参数库'!$A$63:$A$84=B45)*('基础核心-参数库'!$B$63:$B$84=B44),0),0)),1)) | C76: 孔径修正：按钻机型号和孔径查表，修正实际钻速
A77: 钻机功率 | B77: =IF(OR(B3="不适用",B3="请选择工艺"),168,IFERROR(VLOOKUP(B45,'基础核心-参数库'!$A$51:$E$58,5,0),168)) | C77: 钻机月有效台班(基准168) = 按代号查参数库
A78: 纯钻速(m/min) | B78: =IF(OR(B3="不适用",B3="请选择工艺"),0,IFERROR(0.8*B75*B76*(B77/168),0)) | C78: 钻机时间利用率 = 0.8×钻速×有效系数×(月台班÷168)
A79: 接杆数 | B79: =IF(OR(B3="不适用",B3="请选择工艺"),0,MAX(ROUNDUP(B67/3,0)-1,0)) | C79: 接杆数 = ROUNDUP(孔深÷3) - 1（每段3m，首段不接杆）
A80: 换杆方式 | B80: =IF(OR(B3="不适用",B3="请选择工艺"),"自动",IFERROR(VLOOKUP(B45,'基础核心-参数库'!$A$51:$F$58,6,0),"自动")) | C80: 换杆方式：钻机表 F$51 查
A81: 接杆总时间(min) | B81: =IF(B80="自动",B79*'基础核心-参数库'!$F$98,B79*'基础核心-参数库'!$G$98) | C81: 接杆总时间 = 接杆数 × 单次接杆时间（自动/人工换杆参数库 F98/G98）
A82: 卸杆总时间(min) | B82: =IF(B80="自动",B79*'基础核心-参数库'!$F$99,B79*'基础核心-参数库'!$G$99) | C82: 卸杆总时间 = 接杆数 × 单次卸杆时间（参数库 F99/G99）
A83: 辅助时间基础(min) | B83: =B81+B82+'基础核心-参数库'!$F$100+'基础核心-参数库'!$F$101 | C83: 辅助时间基础 = 接杆+卸杆+移位(F100)+清孔(F101)
A84: 钻孔深度效率修正系数 | B84: =1+MAX(0,B67-10)/10*0.05 | C84: 孔深>10m时每超1m，效率-0.5% 公式：1 + MAX(0, 孔深-10)/10 × 0.05
A85: 辅助时间(min) | B85: =B83*B84 | C85: 实际辅助时间 = 辅助基础 × 深度系数(B84)
A86: 总时间/孔(min) | B86: =IFERROR(B67/B78+B85,0) | C86: 每孔钻孔时间(分) = 孔深÷钻速 × 深度系数
A87: 台班进尺(m) | B87: =IF(OR(B3="不适用",B3="请选择工艺"),0,'基础核心-参数库'!$Z$10*60*'基础核心-参数库'!$Z$15/B86*B67) | C87: 每台班钻孔米数 = 台班分钟【Z10×60=480】×钻机时间利用率【Z15=0.75】÷每孔时间×孔深
A89: --- 单方钻孔成本计算 ---
A90: 钻机原值(万元) | B90: =IF(OR(B3="不适用",B3="请选择工艺"),0,IFERROR(VLOOKUP(B45,'基础核心-参数库'!$A$51:$K$58,11,0),0)) | C90: 钻机原值(万元)：按代号查参数库 K$51
A91: 小时消耗 | B91: =IF(OR(B3="不适用",B3="请选择工艺"),0,IFERROR(VLOOKUP(B45,'基础核心-参数库'!$A$51:$I$58,9,0),0)) | C91: 钻机小时油耗：按代号查参数库 I$51
A92: 动力类型 | B92: =IF(OR(B3="不适用",B3="请选择工艺"),"柴油",IFERROR(VLOOKUP(B45,'基础核心-参数库'!$A$51:$D$58,4,0),"柴油")) | C92: 钻机动力类型：参数库 D$51 查
A93: 机械效率 | B93: =IF(B92="柴油",'基础核心-参数库'!$Z$11,'基础核心-参数库'!$Z$12) | C93: 钻机机械效率：柴油=【常量Z11=0.75】，电=【Z12=0.85】
A94: 折旧+维修费(元/台班) | B94: =(B90*10000*(1-IFERROR(VLOOKUP(B45,'基础核心-参数库'!$A$51:$M$58,13,0),0.05))/IFERROR(VLOOKUP(B45,'基础核心-参数库'!$A$51:$L$58,12,0),4000))*'基础核心-参数库'!$Z$5 | C94: 钻机折旧维修=原值(K$51)×(1-残值率M$51)÷耐用台班(L$51)×系数【常量Z5=1.8】
A95: 能源费(元/台班) | B95: =IF(OR(B3="不适用",B3="请选择工艺"),0,B91*'基础核心-参数库'!$Z$10*IF(B92="柴油",'基础核心-参数库'!$B$3,'基础核心-参数库'!$B$4)/B93) | C95: 钻机能源=小时油耗×台班小时【Z10=8】×单价÷效率
A96: 保险费(元/台班) | B96: =IF(OR(B3="不适用",B3="请选择工艺"),0,B90*10000*'基础核心-参数库'!$B$19/'基础核心-参数库'!$B$18) | C96: 钻机保险 = 原值×保险率÷年台班
A97: 自有台班费(元) | B97: =IF(OR(B3="不适用",B3="请选择工艺"),0,B94+B95+B96+'基础核心-参数库'!$B$5) | C97: 钻机自有台班费 = 折旧维修(B94)+能源(B95)+保险(B96)+机手(B5=300)
A98: 租赁台班费(元) | B98: =IF(OR(B3="不适用",B3="请选择工艺"),0,MAX(IFERROR(VLOOKUP(B45,'基础核心-参数库'!$A$51:$N$58,14,0),0),B97*1.05)) | C98: 钻机租赁台班费 = MAX(参数库 N$51 查, 自有费 B97 × 1.05) ←v10兜底防倒挂
A99: 台班费(元) | B99: =IF(OR(B3="不适用",B3="请选择工艺"),0,IF(B46="自有",B97,B98)) | C99: 钻机台班费 = 自有(B97) 或 租赁(B98)，按钻机来源(B46)取
A100: 钻孔费(元/m) | B100: =IF(OR(B3="不适用",B3="请选择工艺"),0,IFERROR(B99/B87,0)) | C100: 钻孔费(元/m) = 台班费 ÷ 每台班钻孔米数(B87)
A101: 耗材费(元/m) | B101: =0 | C101: 耗材费(元/m)：钻头/钻杆磨耗未单独建模，按0处理（已含在折旧维修系数1.8里）
A102: 钻孔综合费(元/m) | B102: =B100+B101 | C102: 钻机每米成本 = 钻机台班费÷每台班钻孔米数
A103: 爆破钻孔费(元/方) | B103: =IF(OR(B3="不适用",B3="请选择工艺"),0,IFERROR(B102/B71,0)) | C103: 钻机摊销到方量 = 每米成本 × 孔深 ÷ 每孔体积

Sheet 计算明细表-挖装成本
A1: 开挖装车成本计算明细表
A2: 开挖费(元/实方) | B2: =IFERROR(B35/B23,0) | C2: 挖机台班费÷台班产量实方
A3: 工艺判断 | B3: =IF(ISBLANK('成本汇总-测算主表'!$B$12),"请选择工艺",'成本汇总-测算主表'!$B$12) | C3: 工艺类型：从主表B12读取
A5: --- 基本参数 ---
A6: f值 | B6: ='成本汇总-测算主表'!$B$5 | C6: f值：从主表B5读取
A7: 松散系数 | B7: ='成本汇总-测算主表'!$B$7 | C7: 松散系数：直接引用主表B7（保证手动覆盖时联动）
A8: 挖机代号 | B8: ='成本汇总-测算主表'!$B$17 | C8: 挖机代号：从主表B17读取
A9: 挖机来源 | B9: ='成本汇总-测算主表'!$B$18 | C9: 挖机来源：从主表B18读取
A10: 斗容(m³) | B10: =IFERROR(VLOOKUP(B8,'基础核心-参数库'!$A$26:$D$36,4,0),2) | C10: 斗容(m³)：按代号从参数库 D$26 查
A11: 工作重量(t) | B11: =IFERROR(VLOOKUP(B8,'基础核心-参数库'!$A$26:$E$36,5,0),20) | C11: 工作重量(t)：按代号查参数库 E$26（影响保险/吨油耗类间接核算）
A12: 动力类型 | B12: =IFERROR(VLOOKUP(B8,'基础核心-参数库'!$A$26:$F$36,6,0),"柴油") | C12: 动力类型：参数库 F$26 查
A13: 小时消耗 | B13: =IFERROR(VLOOKUP(B8,'基础核心-参数库'!$A$26:$H$36,8,0),20) | C13: 小时油耗(L/h)或耗电(kWh/h)：按代号查参数库 H$26
A14: 机械效率 | B14: =IF(B12="柴油",'基础核心-参数库'!$Z$11,'基础核心-参数库'!$Z$12) | C14: 机械效率：柴油=【常量Z11=0.75】，电=【Z12=0.85】
A15: 工艺类型装车效率系数 | B15: =IF(B3="直接开挖",'基础核心-参数库'!$Z$18,'基础核心-参数库'!$Z$19) | C15: 装车效率：直接开挖【Z18=1.0】，爆破后岩石松散【Z19=1.4】
A16: 岩石硬度与挖掘循环时间修正系数 | B16: =1+MAX(0,B6-5)*0.02 | C16: f=5（Ⅳ级中硬岩）是绝大多数露天矿山的典型工况。f≤5时，常规挖机可以正常高效作业，无需修正；f>5时，岩石越硬，挖掘循环时间越长，需要修正。f每增加1，挖掘斗杆插入阻力增加约5~8%，但通过操作技巧（分层挖掘、慢速作业），实际效率下降约2%。
A18: 台班工程量计算
A19: 工艺类型满斗系数 | B19: =IF(B3="直接开挖",'基础核心-参数库'!$Z$20,'基础核心-参数库'!$Z$21) | C19: 满斗系数：直接开挖【Z20=1.05】，爆破后块度均匀【Z21=1.10】
A20: 基准循环时间(秒) | B20: =IFERROR(4.158*LN(B11*1000)-25.058+MAX(0,(B11-30))*0.2,20) | C20: 装载循环时间(秒)=4.158×LN(工作重量×1000)-25.058 + MAX(0,工作重量-30)×0.2【30吨以上每吨加0.2秒，覆盖大机回转/对位时间】
A21: 循环时间(秒) | B21: =B20*B16*B15 | C21: 工艺时间修正 = 装载循环时间(B20)×松散修正(B15)×f值修正(B16)
A22: 台班产量松方(m³) | B22: =B10*B19*(3600/B21)*'基础核心-参数库'!$Z$10*'基础核心-参数库'!$Z$14*'基础核心-参数库'!$B$21 | C22: 台班产量(松方) = 斗容×满斗×(3600÷循环时间)×台班小时【Z10=8】×挖机时间利用率【Z14=0.80】×工作面折减
A23: 台班产量实方(m³) | B23: =B22/B7 | C23: 台班产量(松方) = 实方 × 松散系数
A25: 台班总成本计算
A26: 原值(万元) | B26: =IFERROR(VLOOKUP(B8,'基础核心-参数库'!$A$26:$J$36,10,0),0) | C26: 原值(万元)：参数库 J$26 查
A27: 耐用台班 | B27: =IFERROR(VLOOKUP(B8,'基础核心-参数库'!$A$26:$K$36,11,0),4000) | C27: 耐用台班：参数库 K$26 查 (=250×常量Z9=2500)
A28: 折旧+维修费(元/台班) | B28: =(B26*10000*(1-IFERROR(VLOOKUP(B8,'基础核心-参数库'!$A$26:$L$36,12,0),0.05))/B27)*'基础核心-参数库'!$Z$4 | C28: 挖机折旧维修=原值(J$26)×(1-残值率L$26)÷耐用台班(K$26)×系数【常量Z4=1.6】
A29: 能源费(元/台班) | B29: =B13*'基础核心-参数库'!$Z$10*IF(B12="柴油",'基础核心-参数库'!$B$3,'基础核心-参数库'!$B$4)/B14 | C29: 挖机能源=小时油耗×台班小时【Z10=8】×单价÷效率
A30: 保险费(元/台班) | B30: =B26*10000*'基础核心-参数库'!$B$19/'基础核心-参数库'!$B$18 | C30: 挖机保险=原值×保险率÷年台班
A31: 人工费(元/台班) | B31: ='基础核心-参数库'!$B$5 | C31: 挖机机手 = 参数库B5(=300元/工日)
A32: 斗齿耗材费(元/台班) | B32: =IFERROR(VLOOKUP(B8,'基础核心-参数库'!$A$26:$N$36,14,0)*8/VLOOKUP(B8,'基础核心-参数库'!$A$26:$O$36,15,0),0) | C32: 斗齿耗材费(元/台班) = 斗齿单价(N$26) × 台班小时【Z10=8】 ÷ 斗齿寿命(O$26,单位h)
A33: 自有台班费(元) | B33: =B28+B29+B30+B31+B32 | C33: 挖机自有台班费 = 折旧+能源+保险+机手+辅助
A34: 租赁台班费(元) | B34: =MAX(IFERROR(VLOOKUP(B8,'基础核心-参数库'!$A$26:$M$36,13,0),0),B33*1.05) | C34: 挖机租赁台班费 = MAX(参数库 M$26 查, 自有费 B33 × 1.05) ←v10兜底防倒挂
A35: 台班费(元) | B35: =IF(B9="自有",B33,B34) | C35: 台班费 = 自有则取自有费，否则取租赁费

Sheet 计算明细表-运输成本
A1: 运输成本计算明细表
A2: 运输费(元/实方) | B2: =IF(AND(B23=0,B24=0),0,IFERROR(B74/B51,0)) | C2: 台班费÷台班运输量（运距为0时运输费=0）
A4: --- 基本参数汇集 ---
A5: f值 | B5: ='成本汇总-测算主表'!$B$5 | C5: f值：主表B5
A6: 实体容重(t/m³) | B6: ='成本汇总-测算主表'!$B$6 | C6: 实体容重：主表B6
A7: 矿卡代号 | B7: ='成本汇总-测算主表'!$B$23 | C7: 矿卡代号：主表B23
A8: 矿卡来源 | B8: ='成本汇总-测算主表'!$B$24 | C8: 矿卡来源：主表B24
A9: 矿卡载重(t) | B9: =IFERROR(VLOOKUP(B7,'基础核心-参数库'!$A$40:$D$47,4,0),45) | C9: 矿卡载重(t)：参数库 D$40 按代号查
A10: 动力类型 | B10: =IFERROR(VLOOKUP(B7,'基础核心-参数库'!$A$40:$E$47,5,0),"柴油") | C10: 动力类型：参数库 E$40 查
A11: 空载消耗(L/km或kWh/km) | B11: =IFERROR(VLOOKUP(B7,'基础核心-参数库'!$A$40:$G$47,7,0),0.25) | C11: 空载油耗/电耗：参数库 G$40 查
A12: 重载上坡消耗(L/km或kWh/km) | B12: =IFERROR(VLOOKUP(B7,'基础核心-参数库'!$A$40:$H$47,8,0),0.55) | C12: 重载上坡油耗/电耗：参数库 H$40 查
A13: 重载下坡消耗(L/km或kWh/km) | B13: =IFERROR(VLOOKUP(B7,'基础核心-参数库'!$A$40:$I$47,9,0),0.55) | C13: 重载下坡油耗/电耗：按代号查参数库 I$40
A14: 空车速度(km/h) | B14: =IFERROR(VLOOKUP(B7,'基础核心-参数库'!$A$40:$O$47,15,0),30) | C14: 空车速度：参数库 O$40 查
A15: 重车速度(km/h) | B15: =IFERROR(VLOOKUP(B7,'基础核心-参数库'!$A$40:$P$47,16,0),20) | C15: 重车速度：参数库 P$40 查
A16: 卸车时间(min) | B16: =IFERROR(VLOOKUP(B7,'基础核心-参数库'!$A$40:$Q$47,17,0),1.5) | C16: 卸车时间：参数库 Q$40 查
A17: 机械效率 | B17: =IF(B10="柴油",'基础核心-参数库'!$Z$11,'基础核心-参数库'!$Z$12) | C17: 机械效率：柴油=【常量Z11=0.75】，电=【Z12=0.85】
A18: 每车实方(m³) | B18: =IFERROR(B9/'成本汇总-测算主表'!$B$6,0) | C18: 车辆载重除以实体容重
A19: 挖机松方产量(m³/台班) | B19: ='计算明细表-挖装成本'!$B$22 | C19: 挖机松方台班产量：从挖装表 B22 取
A20: 装车时间(min) | B20: =ROUNDUP(B18*'计算明细表-挖装成本'!$B$7/('计算明细表-挖装成本'!$B$10*'计算明细表-挖装成本'!$B$19),0)*'计算明细表-挖装成本'!$B$21/60 | C20: 装车时间(min) = 每车实方×松散系数÷(挖机实方/秒×装满系数)×循环时间÷60
A22: --- 运距参数汇集 ---
A23: 场内距离(km) | B23: ='成本汇总-测算主表'!$B$34 | C23: 场内距离：主表B34
A24: 场外距离(km) | B24: ='成本汇总-测算主表'!$B$35 | C24: 场外距离：主表B35
A25: 场内重车方向 | B25: ='成本汇总-测算主表'!$B$37 | C25: 场内重车方向：主表B37
A26: 场内坡度(%) | B26: ='成本汇总-测算主表'!$B$38 | C26: 场内坡度：主表B38
A27: 场外重车方向 | B27: ='成本汇总-测算主表'!$B$39 | C27: 场外重车方向：主表B39
A28: 场外坡度(%) | B28: ='成本汇总-测算主表'!$B$40 | C28: 场外坡度：主表B40
A29: 场内空车方向 | B29: =IF(B25="上坡","下坡",IF(B25="下坡","上坡","平路")) | C29: 场内空车方向：与重车方向相反
A30: 场外空车方向 | B30: =IF(B27="上坡","下坡",IF(B27="下坡","上坡","平路")) | C30: 场外空车方向：与重车方向相反
A32: --- 速度修正系数 ---
A33: 场内系数
A34: 场内重车速度系数 | B34: =MAX(IFERROR(SUMIFS('基础核心-参数库'!$V$40:$V$44,'基础核心-参数库'!$R$40:$R$44,B25,'基础核心-参数库'!$S$40:$S$44,"<="&B26,'基础核心-参数库'!$T$40:$T$44,">"&B26),0),IF(B25="平路",1,IF(B25="上坡",0.75,0.9))) | C34: 场内重车速度系数：SUMIFS按方向+坡度区间查 V$40:V$44
A35: 场内空车速度系数 | B35: =MAX(IFERROR(SUMIFS('基础核心-参数库'!$U$40:$U$44,'基础核心-参数库'!$R$40:$R$44,B29,'基础核心-参数库'!$S$40:$S$44,"<="&B26,'基础核心-参数库'!$T$40:$T$44,">"&B26),0),IF(B29="平路",1,IF(B29="上坡",0.85,1.05))) | C35: 场内空车速度系数：SUMIFS查 U$40:U$44
A36: 场外重车速度系数 | B36: =MAX(IFERROR(SUMIFS('基础核心-参数库'!$V$40:$V$44,'基础核心-参数库'!$R$40:$R$44,B27,'基础核心-参数库'!$S$40:$S$44,"<="&B28,'基础核心-参数库'!$T$40:$T$44,">"&B28),0),IF(B27="平路",1,IF(B27="上坡",0.75,0.9))) | C36: 场外重车速度系数：同上查 V列
A37: 场外空车速度系数 | B37: =MAX(IFERROR(SUMIFS('基础核心-参数库'!$U$40:$U$44,'基础核心-参数库'!$R$40:$R$44,B30,'基础核心-参数库'!$S$40:$S$44,"<="&B28,'基础核心-参数库'!$T$40:$T$44,">"&B28),0),IF(B30="平路",1,IF(B30="上坡",0.85,1.05))) | C37: 场外空车速度系数：同上查 U列
A38: 场外系数
A39: 场内重车速度(km/h) | B39: =B15*B34 | C39: 场内重车实际速度 = 重车速度(B15) × 系数(B34)
A40: 场内空车速度(km/h) | B40: =B14*B35 | C40: 场内空车实际速度 = 空车速度(B14) × 系数(B35)
A41: 场外重车速度(km/h) | B41: =B15*B36 | C41: 场外重车实际速度 = 重车速度 × 系数(B36)
A42: 场外空车速度(km/h) | B42: =B14*B37 | C42: 场外空车实际速度 = 空车速度 × 系数(B37)
A44: --- 台班方量计算 ---
A45: 场内重车时间(min) | B45: =IFERROR(B23/B39*60,0) | C45: 场内重车时间(min) = 距离÷速度×60
A46: 场内空车时间(min) | B46: =IFERROR(B23/B40*60,0) | C46: 场内空车时间(min) = 距离÷速度×60
A47: 场外重车时间(min) | B47: =IFERROR(B24/B41*60,0) | C47: 场外重车时间(min) = 距离÷速度×60
A48: 场外空车时间(min) | B48: =IFERROR(B24/B42*60,0) | C48: 场外空车时间(min) = 距离÷速度×60
A49: 总循环时间(min) | B49: =MAX(B20+B16+B45+B46+B47+B48,3) | C49: 总循环时间 = 装车+卸车+四段行车 (最低3分钟保护)
A50: 台班趟数 | B50: ='基础核心-参数库'!$Z$10*60*'基础核心-参数库'!$Z$13/B49 | C50: 台班趟数 = 台班分钟【Z10×60=480】×矿卡时间利用率【Z13=0.85】÷循环时间
A51: 台班运输量(实方) | B51: =B50*B18 | C51: 台班运输量(实方) = 趟数 × 每车实方(B18)
A53: --- 能源费计算 --- | D53: 矿卡油耗主要由三部分组成：
A54: 场内重车能耗系数 | B54: =MAX(IFERROR(IF(B10="柴油",SUMIFS('基础核心-参数库'!$W$40:$W$44,'基础核心-参数库'!$R$40:$R$44,B25,'基础核心-参数库'!$S$40:$S$44,"<="&B26,'基础核心-参数库'!$T$40:$T$44,">"&B26),SUMIFS('基础核心-参数库'!$X$40:$X$44,'基础核心-参数库'!$R$40:$R$44,B25,'基础核心-参数库'!$S$40:$S$44,"<="&B26,'基础核心-参数库'!$T$40:$T$44,">"&B26)),0),IF(B25="平路",1,IF(B25="上坡",1.15,0.9))) | C54: 场内重车能耗系数：SUMIFS按方向+坡度查油耗系数(W列柴油/X列电) | D54: 滚动阻力（轮胎与地面摩擦）：与载重正相关
A55: 场内空车能耗系数 | B55: =MAX(IFERROR(IF(B10="柴油",SUMIFS('基础核心-参数库'!$W$40:$W$44,'基础核心-参数库'!$R$40:$R$44,B29,'基础核心-参数库'!$S$40:$S$44,"<="&B26,'基础核心-参数库'!$T$40:$T$44,">"&B26),SUMIFS('基础核心-参数库'!$X$40:$X$44,'基础核心-参数库'!$R$40:$R$44,B29,'基础核心-参数库'!$S$40:$S$44,"<="&B26,'基础核心-参数库'!$T$40:$T$44,">"&B26)),0),IF(B29="平路",1,IF(B29="上坡",1.15,0.9))) | C55: 场内空车能耗系数：同上 | D55: 空气阻力（迎风）：与车速正相关，与载重无关
A56: 场外重车能耗系数 | B56: =MAX(IFERROR(IF(B10="柴油",SUMIFS('基础核心-参数库'!$W$40:$W$44,'基础核心-参数库'!$R$40:$R$44,B27,'基础核心-参数库'!$S$40:$S$44,"<="&B28,'基础核心-参数库'!$T$40:$T$44,">"&B28),SUMIFS('基础核心-参数库'!$X$40:$X$44,'基础核心-参数库'!$R$40:$R$44,B27,'基础核心-参数库'!$S$40:$S$44,"<="&B28,'基础核心-参数库'!$T$40:$T$44,">"&B28)),0),IF(B27="平路",1,IF(B27="上坡",1.15,0.9))) | C56: 场外重车能耗系数：同上 | D56: 爬坡功（克服重力做功）：与坡度、载重正相关
A57: 场外空车能耗系数 | B57: =MAX(IFERROR(IF(B10="柴油",SUMIFS('基础核心-参数库'!$W$40:$W$44,'基础核心-参数库'!$R$40:$R$44,B30,'基础核心-参数库'!$S$40:$S$44,"<="&B28,'基础核心-参数库'!$T$40:$T$44,">"&B28),SUMIFS('基础核心-参数库'!$X$40:$X$44,'基础核心-参数库'!$R$40:$R$44,B30,'基础核心-参数库'!$S$40:$S$44,"<="&B28,'基础核心-参数库'!$T$40:$T$44,">"&B28)),0),IF(B30="平路",1,IF(B30="上坡",1.15,0.9))) | C57: 场外空车能耗系数：同上 | D57: 平路场景只有 1+2，没有 3；上坡场景三项全有。所以平路油耗一定大于空车（载重让滚阻变大），但远小于上坡（没有爬坡功）。
A58: 动力单价(元/L或kWh) | B58: =IF(B10="柴油",'基础核心-参数库'!$B$3,'基础核心-参数库'!$B$4) | C58: 动力单价：柴油=B3(7.5)，电=B4(0.65) | D58: 为什么不能用 (上坡+下坡)/2
A59: 场内重车能源费/趟 | B59: =IF(B25="上坡",B12,IF(B25="下坡",B13,B11+(B12-B11)*'基础核心-参数库'!$Z$7))*B23*B54*B58*(IF(B25="上坡",1+B26*'基础核心-参数库'!$Z$25,IF(B25="下坡",MAX(0.7,1-B26*'基础核心-参数库'!$Z$26),1+B26*'基础核心-参数库'!$Z$25*0.5))) | C59: 场内重车能源费/趟 = 基础油耗×距离×速度系数×单价 × slope_modifier(连续坡度修正,Z25/Z26) | D59: 下坡时重力做正功，发动机几乎只是怠速，油耗接近"空车"
A60: 场内空车能源费/趟 | B60: =B11*B23*B55*B58 | C60: 场内空车能源费/趟 = 空载油耗×距离×系数×单价 | D60: 上坡的高油耗主要来自爬坡功
A61: 场外重车能源费/趟 | B61: =IF(B27="上坡",B12,IF(B27="下坡",B13,B11+(B12-B11)*'基础核心-参数库'!$Z$7))*B24*B56*B58*(IF(B27="上坡",1+B28*'基础核心-参数库'!$Z$25,IF(B27="下坡",MAX(0.7,1-B28*'基础核心-参数库'!$Z$26),1+B28*'基础核心-参数库'!$Z$25*0.5))) | C61: 场外重车能源费/趟 = 同B59，公式参数换场外 | D61: 平均值物理意义不对，会高估平路油耗 30-50%
A62: 场外空车能源费/趟 | B62: =B11*B24*B57*B58 | C62: 场外空车能源费/趟 = 空载油耗×距离×系数×单价 | D62: 负载因子取值依据
A63: 每趟能源费(元) | B63: =MAX(0,B59+B60+B61+B62) | C63: 每趟能源费 = 四段能源费之和 (≥0)
D64: 工况 | E64: 负载因子 | F64: 说明
A65: --- 台班费计算 --- | D65: 0.15 | E65: 高速公路、油门稳定 | F65: 风阻占主导，载重影响小
A66: 原值(万元) | B66: =IFERROR(VLOOKUP(B7,'基础核心-参数库'!$A$40:$K$47,11,0),200) | C66: 矿卡原值(万元)：参数库 K$40 查 | D66: 0.2 | E66: 矿区平整硬质路面 | F66: 推荐用于场外公路短倒
A67: 耐用台班 | B67: =IFERROR(VLOOKUP(B7,'基础核心-参数库'!$A$40:$L$47,12,0),3500) | C67: 矿卡耐用台班：参数库 L$40 查 (=250×常量Z8=2000) | D67: 0.25 | E67: 矿区一般路面（默认） | F67: 推荐用于多数场景
A68: 折旧+维修费(元/台班) | B68: =(B66*10000*(1-IFERROR(VLOOKUP(B7,'基础核心-参数库'!$A$40:$M$47,13,0),0.05))/B67)*'基础核心-参数库'!$Z$3 | C68: 矿卡折旧维修=原值(K$40)×(1-残值率M$40)÷耐用台班(L$40)×系数【常量Z3=1.5】 | D68: 0.3 | E68: 矿区粗糙/松软路面 | F68: 推荐用于场内便道
A69: 保险费(元/台班) | B69: =B66*10000*'基础核心-参数库'!$B$19/'基础核心-参数库'!$B$18 | C69: 矿卡保险 = 原值×保险率÷年台班 | D69: 0.40+ | E69: 烂路、积水、起伏路 | F69: 滚阻显著增加
A70: 台班基础费(元) | B70: =B68+B69+'基础核心-参数库'!$B$5 | C70: 台班基础费 = 折旧维修+保险+机手(参数库B5=300)
A71: 台班能源费(元) | B71: =B50*B63 | C71: 台班能源费 = 趟数 × 每趟能源费
A72: 自有台班费(元) | B72: =B70+B71 | C72: 自有台班费 = 基础费(B70) + 能源费(B71)
A73: 租赁台班费(元) | B73: =MAX(IFERROR(VLOOKUP(B7,'基础核心-参数库'!$A$40:$N$47,14,0),3000),B72*1.05) | C73: 矿卡租赁台班费 = MAX(参数库 N$40 查, 自有费 B72 × 1.05) ←v10兜底防倒挂
A74: 台班费(元) | B74: =IF(B8="自有",B72,B73) | C74: 台班费 = 自有则取自有，否则取租赁

Sheet 计算明细表-钩机松土成本
A1: 钩机松土成本计算明细表
A2: 松土费(元/实方) | B2: =IFERROR(B11/B10+B12,0) | C2: 松土费 = 挖机台班费÷松土器台班产量 + 齿尖耗材费
A3: f值 | B3: ='成本汇总-测算主表'!$B$5 | C3: f值：主表B5
A4: 挖机代号 | B4: ='成本汇总-测算主表'!$B$17 | C4: 挖机代号：主表B17
A5: 挖机来源 | B5: ='成本汇总-测算主表'!$B$18 | C5: 挖机来源：主表B18
A6: 斗容(m³) | B6: =IFERROR(VLOOKUP(B4,'基础核心-参数库'!$A$26:$D$36,4,0),2) | C6: 斗容(m³)：按代号查参数库 D$26
A7: 岩石硬度松土器作业效率系数 | B7: {=IFERROR(IF(B3<='基础核心-参数库'!$D$13,INDEX('基础核心-参数库'!$H$13:$H$22,MATCH('基础核心-参数库'!$D$13,'基础核心-参数库'!$D$13:$D$22,0)),IF(B3>='基础核心-参数库'!$D$22,INDEX('基础核心-参数库'!$H$13:$H$22,MATCH('基础核心-参数库'!$D$22,'基础核心-参数库'!$D$13:$D$22,0)),INDEX('基础核心-参数库'!$H$13:$H$22,MATCH(B3,'基础核心-参数库'!$D$13:$D$22,1))+(B3-INDEX('基础核心-参数库'!$D$13:$D$22,MATCH(B3,'基础核心-参数库'!$D$13:$D$22,1)))*(INDEX('基础核心-参数库'!$H$13:$H$22,MATCH(B3,'基础核心-参数库'!$D$13:$D$22,1)+1)-INDEX('基础核心-参数库'!$H$13:$H$22,MATCH(B3,'基础核心-参数库'!$D$13:$D$22,1)))/(INDEX('基础核心-参数库'!$D$13:$D$22,MATCH(B3,'基础核心-参数库'!$D$13:$D$22,1)+1)-INDEX('基础核心-参数库'!$D$13:$D$22,MATCH(B3,'基础核心-参数库'!$D$13:$D$22,1))))),0)} | C7: 松土器效率系数：f值插值，2~0，f越大效率越低，f>14时松土器基本失效。
A8: 工艺顺序错配惩罚系数（松土器） | B8: =IFERROR(IF(AND('成本汇总-测算主表'!$B$13="爆破+开挖",'成本汇总-测算主表'!$B$12="松土器松土+开挖"),VLOOKUP("爆破→松土",'基础核心-参数库'!$M$3:$O$7,2,0),IF(AND('成本汇总-测算主表'!$B$13="松土器松土+开挖",'成本汇总-测算主表'!$B$12="机械破碎+开挖"),VLOOKUP("松土→破碎",'基础核心-参数库'!$M$3:$O$7,2,0),1)),1) | C8: 工艺错配惩罚：爆破→松土 ×0.2（极不推荐）；松土→破碎 ×0.7（勉强可接受）。
A9: 工艺错配齿尖消耗倍率 | B9: =IFERROR(IF(AND('成本汇总-测算主表'!$B$13="爆破+开挖",'成本汇总-测算主表'!$B$12="松土器松土+开挖"),VLOOKUP("爆破→松土",'基础核心-参数库'!$M$3:$O$7,3,0),IF(AND('成本汇总-测算主表'!$B$13="松土器松土+开挖",'成本汇总-测算主表'!$B$12="机械破碎+开挖"),VLOOKUP("松土→破碎",'基础核心-参数库'!$M$3:$O$7,3,0),1)),1) | C9: 耗材费倍率：工艺顺序错误时，齿尖消耗成倍增加，爆破→松土 ×5.0，松土→破碎 ×1.5。
A10: 松土器台班产量(实方) | B10: =IFERROR(B7*INDEX('基础核心-参数库'!$B$119:$B$124,MATCH(B3,'基础核心-参数库'!$A$119:$A$124,1))*(B6/2)*'基础核心-参数库'!$Z$22*'基础核心-参数库'!$Z$16*'基础核心-参数库'!$B$21,0)*B8 | C10: 松土器台班产量 = 工艺效率×松土斗系数×(斗容÷2)×斗容利用率【Z22=0.85】×松土器时间利用率【Z16=0.70】×工作面折减(B21)×错配惩罚
A11: 挖机台班费(元) | B11: ='计算明细表-挖装成本'!$B$35 | C11: 与开挖设备同型号，但更换了钩机头，故台班费用与所选挖机费用一致。
A12: 齿尖耗材费(元/方) | B12: =IFERROR('基础核心-参数库'!$B$12/'基础核心-参数库'!$B$13,0)*B9 | C12: 齿尖耗材费 = 齿尖单价(B12)÷寿命(B13) × 错配消耗倍率(B9)

Sheet 计算明细表-机械破碎成本
A1: 机械破碎成本计算明细表
A2: 破碎费(元/实方) | B2: =IFERROR(B11/B10+B12,0) | C2: 破碎费 = 挖机台班费÷破碎台班产量 + 钎杆耗材费
A3: f值 | B3: ='成本汇总-测算主表'!$B$5 | C3: f值：主表B5
A4: 挖机代号 | B4: ='成本汇总-测算主表'!$B$17 | C4: 挖机代号：主表B17
A5: 挖机来源 | B5: ='成本汇总-测算主表'!$B$18 | C5: 挖机来源：主表B18
A6: 斗容(m³) | B6: =IFERROR(VLOOKUP(B4,'基础核心-参数库'!$A$26:$D$36,4,0),2) | C6: 斗容(m³)：按代号查参数库 D$26
A7: 岩石硬度破碎锤作业效率系数 | B7: {=IFERROR(IF(B3<='基础核心-参数库'!$D$13,INDEX('基础核心-参数库'!$I$13:$I$22,MATCH('基础核心-参数库'!$D$13,'基础核心-参数库'!$D$13:$D$22,0)),IF(B3>='基础核心-参数库'!$D$22,INDEX('基础核心-参数库'!$I$13:$I$22,MATCH('基础核心-参数库'!$D$22,'基础核心-参数库'!$D$13:$D$22,0)),INDEX('基础核心-参数库'!$I$13:$I$22,MATCH(B3,'基础核心-参数库'!$D$13:$D$22,1))+(B3-INDEX('基础核心-参数库'!$D$13:$D$22,MATCH(B3,'基础核心-参数库'!$D$13:$D$22,1)))*(INDEX('基础核心-参数库'!$I$13:$I$22,MATCH(B3,'基础核心-参数库'!$D$13:$D$22,1)+1)-INDEX('基础核心-参数库'!$I$13:$I$22,MATCH(B3,'基础核心-参数库'!$D$13:$D$22,1))))),0)} | C7: 破碎锤效率系数：f值插值，1.2~0.5，f越大效率越低 比松土器适用范围更广（f到22仍有效）
A8: 工艺顺序错配惩罚系数（破碎锤） | B8: =IFERROR(IF(AND('成本汇总-测算主表'!$B$13="爆破+开挖",OR('成本汇总-测算主表'!$B$12="机械破碎+开挖",'成本汇总-测算主表'!$B$12="爆破+二次破碎+开挖")),VLOOKUP("爆破→破碎",'基础核心-参数库'!$M$3:$O$7,2,0),IF(AND('成本汇总-测算主表'!$B$13="松土器松土+开挖",OR('成本汇总-测算主表'!$B$12="机械破碎+开挖",'成本汇总-测算主表'!$B$12="爆破+二次破碎+开挖")),VLOOKUP("松土→破碎",'基础核心-参数库'!$M$3:$O$7,2,0),1)),1) | C8: 工艺错配惩罚：爆破→破碎 ×0.5（不推荐），松土→破碎 ×0.7（勉强可接受）
A9: 工艺错配钎杆消耗倍率 | B9: =IFERROR(IF(AND('成本汇总-测算主表'!$B$13="爆破+开挖",OR('成本汇总-测算主表'!$B$12="机械破碎+开挖",'成本汇总-测算主表'!$B$12="爆破+二次破碎+开挖")),VLOOKUP("爆破→破碎",'基础核心-参数库'!$M$3:$O$7,3,0),IF(AND('成本汇总-测算主表'!$B$13="松土器松土+开挖",OR('成本汇总-测算主表'!$B$12="机械破碎+开挖",'成本汇总-测算主表'!$B$12="爆破+二次破碎+开挖")),VLOOKUP("松土→破碎",'基础核心-参数库'!$M$3:$O$7,3,0),1)),1) | C9: 耗材费倍率：工艺顺序错误时，钎杆消耗成倍增加，爆破→破碎 ×3.0，松土→破碎 ×1.5。
A10: 破碎台班产量(实方) | B10: =IFERROR(B7*INDEX('基础核心-参数库'!$D$119:$D$124,MATCH(B3,'基础核心-参数库'!$C$119:$C$124,1))*(B6/2)*'基础核心-参数库'!$Z$22*'基础核心-参数库'!$Z$17*'基础核心-参数库'!$B$21,0)*B8 | C10: 破碎台班产量 = 工艺效率×破碎锤系数×(斗容÷2)×斗容利用率【Z22=0.85】×破碎锤时间利用率【Z17=0.65】×工作面折减(B21)×错配惩罚
A11: 挖机台班费(元) | B11: ='计算明细表-挖装成本'!$B$35 | C11: 挖机台班费 = 取挖装表B35（同挖机型号、换破碎锤）
A12: 钎杆耗材费(元/方) | B12: =IFERROR('基础核心-参数库'!$B$9/'基础核心-参数库'!$B$10,0)*B9 | C12: 钎杆耗材费 = 钎杆单价(B9)÷寿命(B10) × 错配消耗倍率
